Workbook

Sheet Home
C2: Climate Risk and Vulnerability Assessment Tool: Communities and Infrastructure Projects
C4: Creating Climate Resilient Communities and Infrastructure
D7: Project Name: | E7: Enter here | Q7: Project Lead: | R7: Enter here
D8: Project Location: | E8: Enter here | Q8: Name of Assessor:
D9: Project Code: | E9: Enter here | Q9: No. of Beneficiaries: | R9: Enter here
H34: This diagram shows that hazards lead to exposure, which, when combined with sensitivity, determines the vulnerability of a system. Adaptive capacity acts as a protective factor, influencing vulnerability and the overall level of risk

Sheet Instructions
B7: AIM:
B8: The objective of the tool is to evaluate the climate risk and vulnerability of communities. The tool assesses how current climate hazards (such as temperature, Precipitation, droughts and floods) impact the broader community. Based on the prevailing risk and vulnerability, the tool explores potential interventions that will improve climate resilience. This tool is focused on assessing the current risk and vulnerability levels for communities. In addition to the assets lens, gender, green infrastructure and the socio-ecological benefits that it provides, is also explored. The tool also uses the updated Intergovernmental Panel on Climate Change (IPCC) methodology, as discussed in detail in the section below.
B12: FRAMEWORK:
B13: In line with the Fifth Assessment Report (AR5) by the Intergovernmental Panel on Climate Change (IPCC), the tool includes the following aspects:
B14: • | C14: Hazard: the occurrence or potential occurrence of a climate-related event (such as rainfall or temperature) and/or a natural or human-induced impact (such as flood or droughts), that has or may cause harm, injury, damage or the loss of a system, species or asset. Exposure: the degree to which a system, species or asset is ‘exposed’, due to its location or presence in a place or setting that is or could be impacted by a climate-related hazard. Sensitivity: the susceptibility of a system, species or asset to climate-related impacts, or the degree to which system, species or asset is or can be directly or indirectly impacted by a climate-related hazard. Adaptive Capacity: the proven or perceived ability of a system, species or asset to respond to existing or potential climate-related impacts and adjust to damage, so as to cope with consequences and take advantage of opportunities. Vulnerability: the inclination of a system, species or asset to be impacted by climate-related hazards, encompassing its sensitivity and its ability to cope or adapt to climate-related impacts. Risk: refers to the potential for (and the likelihood of) adverse climate-related impacts on a system, species or asset, resulting from the interaction of vulnerability, exposure, and hazard.
B16: •
B17: •
B19: •
B21: •
B22: •
B26: The tool relies on several questions that assess hazard, exposure, sensitivity and adaptive capacity. As shown above, the responses to these categories, will enable an assessment of risk and vulnerability will be assessed. Based on the prevalent risk and vulnerability, the tool explores potential response measures that will improve climate resilience by either decreasing sensitivity or increasing adaptive capacity. In addition, whenever possible, measures to decrease exposure will be explored.
B31: HOW TO USE THIS TOOL:
B32: The grey rectangular boxes enable the user to explore through the tool. The boxes will either lead the user to a different place in the same rectanglar tab, or to a new rectanglar tab. Therefore, please click on any grey box to navigate and to complete the tool. The user is required to answer the questions provided under the "Hazard" rectanglar tab, "Exposure" rectanglar tab, "Sensitivity" rectanglar tab, as well as the "Adaptive Capacity" rectanglar tab. The user can access these rectanglar tabs by clicking on the "Hazard", "Exposure", "Sensitivity", and the "Adaptive Capacity" boxes. In these rectanglar tabs, questions are provided for "Hazard", "Exposure", "Sensitivity", and "Adaptive Capacity". The "Output" rectanglar tab leads the user to the "RVAT" rectanglar tab, where the answer to each question are analysed using the framework, assessed and graphed. Specifically, the tool provides outputs for "Vulnerability" and "Risk". Based on the “Risk” output, which incorporates “vulnerability”, the tool provides response options. These can be accessed by clicking on the "Responses" rectanglar tab at the top of your screen, or by clicking the "Responses" rectanglar tab.
B46: USEFUL RESOURCES:
B47: Below is a source to help answer some of the questions:
B48: 1 | C48: WRI - Aqueduct Water Risk Atlas. Link: | L48: http://www.wri.org/resources/maps/aqueduct-water-risk-atlas
B51: ABBREVIATIONS USED
B52: 1. LUI=Land Use Inadiquacy 2. WFI/WFDU=Water for irrigation/Water for domestic use 3. ATF/I=Access to finance/insurance 4. SLUP & C=Safety land use planning and control 5. SWM=Solid waste management 6. LWM=Liquid waste management 6. ATHS=Access to health services 7. ATHE=Access to healthy environment 8. SWD=Storm water drainage 9. PWT=Portable water treatment 10. R & T=Road and transport 11. LC &P=Land cover and permeability 12. NV=Natural Vegetation 13. NWB=Natural water bodies 14. EF=Ecosystem functionality 15. EWS=Early warning systems 16. A & I=Awareness and information 17. EC=Engagement with county community 18. R/RP= Resource/resources planning 19. HFO=Health facilities operations 20. DP=Disaster preparedness 21. DR=Disaster responce 22. PFR=Public finance/recovery grands 23. PFM=Public finanace/maintenance NB: All abbreviations have their full meaning in the comments section.
B55: NOTE: 1. This tool has been developed using MS Excel 2019, and therefore, any verions before 2019 may have limited funcitonality. 2. As this tool uses several macros to enable functionality, the user is required to click on the "Enable macros" button when prompted. 3. To ensure the usability of the tool is maintained, please avoid deleting any rows and columns. As the functionality of the tool is maximised with coding, any modifications of the spreadsheets will render it useless. 4. The tool has default data that depics an ideal informal settlement, amend where applicable only.
U66: Developed for KISIP by:

Sheet Hazard
F7: NOTE: ONCE YOU CLICK THIS BUTTON YOU CANNOT UNDO YOUR ACTIONS
B8: CURRENT HAZARDS | J8: No Selection Done!
B10: Hazard | E10: Question | F10: Comments/Description | G10: Answer? | H10: Add Note On Each Answer | I10: Rating? | J10: List 1 | K10: yes/no is bad
A11: 1 | B11: 1 | C11: Temperature | D11: App or Freq | E11: Are extreme temperatures frequentlly experienced in the settlement? | F11: During the year (across seasons), is temperature higher/lower than usual? | G11: Yes, lower than usual | H11: =IF(OR(G11=$J$11,G11=$J$12,G11=$J$13),$J$9,$J$8) | I11: =IF(G11=$J$11,$K$11,IF(G11=$J$12,$K$12,$K$13)) -> 3 | J11: Yes, higher than usual | K11: 3
A12: =A11+1 -> 2 | D12: Intensity | E12: Are the tempereture intensities increasing? | F12: Over multiple years (i.e. trend), is temperature higher/lower than usual? | G12: No, not really | H12: =IF(OR(G12=$J$11,G12=$J$12,G12=$J$13),$J$9,$J$8) | I12: =IF(G12=$J$11,$K$11,IF(G12=$J$12,$K$12,$K$13)) -> 1 | J12: No, not really | K12: 1
A13: =A12+1 -> 3 | D13: Impact | E13: Are there effects on community members being attributed to extreme temperature? | F13: How often do you experience heat-related effects e.g. heat-related stress, heat srokes, effects on elderly? | G13: No | H13: =IF(OR(G13=$J$16,G13=$J$17,G13=$J$18),$J$9,$J$8) | I13: =IF(G13=$J$16,$K$16,IF(G13=$J$17,$K$17,$K$18)) -> 1 | J13: Yes, lower than usual | K13: 3
I14: =""
A15: =A14+1 -> 1 | B15: 2 | C15: Intense Precipitation | D15: App or Freq | E15: Are heavy rainfall events prevalent in this settlement? | F15: During the year (across seasons), is rainfall higher/lower than usual? | G15: No, not really | H15: =IF(OR(G15=$J$11,G15=$J$12,G15=$J$13),$J$9,$J$8) | I15: =IF(G15=$J$11,$K$11,IF(G15=$J$12,$K$12,$K$13)) -> 1 | J15: List 2 | K15: yes is bad
A16: =A15+1 -> 2 | D16: Intensity | E16: Are rainfall intensities and/or durations increasing? | F16: Over multiple years (i.e. trend), is rainfall higher/lower than usual? | G16: No, not really | H16: =IF(OR(G16=$J$11,G16=$J$12,G16=$J$13),$J$9,$J$8) | I16: =IF(G16=$J$11,$K$11,IF(G16=$J$12,$K$12,$K$13)) -> 1 | J16: Yes | K16: 3
A17: =A16+1 -> 3 | D17: Impact | E17: Are there significant effects on the community being attributed to extreme rainfalls? | F17: Are there rainfall effects, example, destruction of crops, houses and normal daily activities? | G17: No | H17: =IF(OR(G17=$J$16,G17=$J$17,G17=$J$18),$J$9,$J$8) | I17: =IF(G17=$J$16,$K$16,IF(G17=$J$17,$K$17,$K$18)) -> 1 | J17: Sometimes | K17: 2
J18: No | K18: 1
A19: =A18+1 -> 1 | B19: 3 | C19: Droughts | D19: App or Freq | E19: Are droughts frequently experienced in the area? | F19: Do you often experience droughts? | G19: No | H19: =IF(OR(G19=$J$31,G19=$J$32,G19=$J$33),$J$9,$J$8) | I19: =IF(G19=$J$16,$K$16,IF(G19=$J$17,$K$17,$K$18)) -> 1
A20: =A19+1 -> 2 | D20: Timing | E20: If droughts do occur, do they occur at the same time of the year? | F20: Is the timing of droughts consistent? | G20: Yes | H20: =IF(OR(G20=$J$31,G20=$J$32,G20=$J$33),$J$9,$J$8) | I20: =IF(G20=$J$31,$K$31,IF(G20=$J$32,$K$32,$K$33)) -> 1 | J20: List 3 | K20: yes is bad
A21: =A20+1 -> 3 | D21: Intensity | E21: If droughts do occur, is the extent and intensity of the drought changing? | F21: Are droughts getting worse or better? | G21: No change | H21: =IF(OR(G21=$J$26,G21=$J$27,G21=$J$28),$J$9,$J$8) | I21: =IF(G21=$J$26,$K$26,IF(G21=$J$27,$K$27,$K$28)) -> 1 | J21: Often | K21: 3
A22: =A21+1 -> 4 | D22: Impact | E22: Are there significant effects on the community being attributed to droughts? | F22: Is the population affected by droughts, example daily activities, livihood? | G22: No | H22: =IF(OR(G22=$J$31,G22=$J$32,G22=$J$33),$J$9,$J$8) | I22: =IF(G22=$J$16,$K$16,IF(G22=$J$17,$K$17,$K$18)) -> 1 | J22: Sometimes | K22: 2
J23: Not applicable | K23: 1
A24: =A23+1 -> 1 | B24: 4 | C24: Flooding | D24: App or Freq | E24: Are seasonal floods prevalent in in the settlement? | F24: Do you often experience rain floods | G24: No | H24: =IF(OR(G24=$J$16,G24=$J$17,G24=$J$18),$J$9,$J$8) | I24: =IF(G24=$J$16,$K$16,IF(G24=$J$17,$K$17,$K$18)) -> 1
A25: =A24+1 -> 2 | D25: Timing | E25: If seasonal floods do occur, do they occur at the same time of the year? | F25: Is the timing of rain floods consistent? | G25: Yes | H25: =IF(OR(G25=$J$31,G25=$J$32,G25=$J$33),$J$9,$J$8) | I25: =IF(G25=$J$31,$K$31,IF(G25=$J$32,$K$32,$K$33)) -> 1 | J25: List 4 | K25: yes is bad
A26: =A25+1 -> 3 | D26: Intensity | E26: If floods do occur, is the intensity icreasing? | F26: Are rain floods getting worse (more impact/intensity) or better (less impact/intensity)? | G26: Yes, but less than 4 days | H26: =IF(OR(G26=$J$53,G26=$J$54,G26=$J$55),$J$9,$J$8) | I26: =IF(G26=$J$53,$K$53,IF(G26=$J$54,$K$54,$K$55)) -> 1 | J26: Yes, but more | K26: 3
A27: =A26+1 -> 4 | D27: Extent | E27: If floods do occur, is the spatial extent increasing ? | F27: Are rain floods getting worse (more impact/intensity) or better (less impact/intensity)? | G27: Less than half | H27: =IF(OR(G27=$J$58,G27=$J$59,G27=$J$60),$J$9,$J$8) | I27: =IF(G27=$J$58,$K$58,IF(G27=$J$59,$K$59,$K$60)) -> 1 | J27: No change | K27: 1
A28: =A27+1 -> 5 | D28: Impact | E28: Are there significant effects on the community being attributed to seasonal floods? | F28: Is the population affected by rain floods? | G28: Not applicable | H28: =IF(OR(G28=$J$21,G28=$J$22,G28=$J$23),$J$9,$J$8) | I28: =IF(G28=$J$21,$K$21,IF(G28=$J$22,$K$22,$K$23)) -> 1 | J28: Yes, but less | K28: 2
A30: =A29+1 -> 1 | B30: 5 | C30: Flash Floods | D30: App or Freq | E30: Are flash floods prevalent in the settlement? | F30: Do you often experience flash floods? | G30: No | H30: =IF(OR(G30=$J$16,G30=$J$17,G30=$J$18),$J$9,$J$8) | I30: =IF(G30=$J$16,$K$16,IF(G30=$J$17,$K$17,$K$18)) -> 1 | J30: List 5 | K30: No is bad
A31: =A30+1 -> 2 | D31: Timing | E31: If flash floods do occur, do they occur at the same time of the year? | F31: Is the timing of flash floods consistent? | G31: No | H31: =IF(OR(G31=$J$31,G31=$J$32,G31=$J$33),$J$9,$J$8) | I31: =IF(G31=$J$16,$K$16,IF(G31=$J$17,$K$17,$K$18)) -> 1 | J31: Yes | K31: 1
A32: =A31+1 -> 3 | D32: Intensity | E32: If flash floods do occur, is the intensity of the flash floods changing? | F32: Are flash floods getting worse (more impact/intensity) or better (less impact/intensity)? | G32: Yes, but less than 4 days | H32: =IF(OR(G32=$J$53,G32=$J$54,G32=$J$55),$J$9,$J$8) | I32: =IF(G32=$J$53,$K$53,IF(G32=$J$54,$K$54,$K$55)) -> 1 | J32: Sometimes | K32: 2
A33: =A32+1 -> 4 | D33: Extent | E33: If flash floods do occur, is the extent of the flash floods changing? | F33: Are flash floods getting worse (more impact/intensity) or better (less impact/intensity)? | G33: Less than half | H33: =IF(OR(G33=$J$58,G33=$J$59,G33=$J$60),$J$9,$J$8) | I33: =IF(G33=$J$58,$K$58,IF(G33=$J$59,$K$59,$K$60)) -> 1 | J33: No | K33: 3
A34: =A33+1 -> 5 | D34: Impact | E34: Are there significant effects on the community being attributed to flash floods? | F34: Is the population affected by flash floods? | G34: Not applicable | H34: =IF(OR(G34=$J$21,G34=$J$22,G34=$J$23),$J$9,$J$8) | I34: =IF(G34=$J$21,$K$21,IF(G34=$J$22,$K$22,$K$23)) -> 1
J35: List 6 | K35: 3 is bad
A36: =A28+1 -> 6 | B36: 6 | C36: Storms & Upper Winds | D36: App or Freq | E36: Are there frequent storm events experienced in the settlement? | F36: During the year (across seasons), is storms/cyclones higher/lower than usual? | G36: No, not really | H36: =IF(OR(G36=$J$11,G36=$J$12,G36=$J$13),$J$9,$J$8) | I36: =IF(G36=$J$11,$K$11,IF(G36=$J$12,$K$12,$K$13)) -> 1 | J36: Combination of all the three | K36: 3
A37: =A36+1 -> 7 | D37: Intensity | E37: Is there increase in frequency and intensity of storms being noted in the settlement? | F37: Over multiple years (i.e. trend), is storms/cyclones higher/lower than usual? | G37: No, not really | H37: =IF(OR(G37=$J$11,G37=$J$12,G37=$J$13),$J$9,$J$8) | I37: =IF(G37=$J$11,$K$11,IF(G37=$J$12,$K$12,$K$13)) -> 1 | J37: Combination of two | K37: 2
A38: =A37+1 -> 8 | D38: Impact | E38: Are there significant effects on the community being attributed to storms? | F38: Are there storms/cyclones effects, example, destruction of crops, houses and normal daily activities? | G38: No | H38: =IF(OR(G38=$J$16,G38=$J$17,G38=$J$18),$J$9,$J$8) | I38: =IF(G38=$J$16,$K$16,IF(G38=$J$17,$K$17,$K$18)) -> 1 | J38: Only one | K38: 1
A40: =A39+1 -> 1 | B40: 7 | C40: Pollution | D40: App or Freq | E40: Is there pollution experienced in the settlement for land, water or soil? | F40: Is there pollution to land, soil and water or combination of two or all? | G40: Only one | H40: =IF(OR(G40=$J$36,G40=$J$37,G40=$J$38),$J$9,$J$8) | I40: =IF(G40=$J$36,$K$36,IF(G40=$J$37,$K$37,$K$38)) -> 1
A41: =A40+1 -> 2 | D41: Intensity | E41: For the selected above, is there an increase of this pollution being noted in the settlement? | F41: Is the polution aspect increasing or decreasing? | G41: Decrease | H41: =IF(OR(G41=$J$42,G41=$J$43,G41=$J$44),$J$9,$J$8) | I41: =IF(G41=$J$42,$K$42,IF(G41=$J$43,$K$43,$K$44)) -> 1 | J41: List 7 | K41: yes is bad
A42: =A41+1 -> 3 | D42: Impact | E42: Are there significant effects on the community being attributed to this pollution? | F42: Are you impacted by pollution that affects daily activities of the population? | G42: No | H42: =IF(OR(G42=$J$16,G42=$J$17,G42=$J$18),$J$9,$J$8) | I42: =IF(G42=$J$16,$K$16,IF(G42=$J$17,$K$17,$K$18)) -> 1 | J42: Increase | K42: 3
J43: Not applicable | K43: 2
A44: =A43+1 -> 1 | B44: 8 | C44: LUI | D44: Applicability | E44: Is there inadequate use of land in sensitive or risky zones? | F44: Are there unstable soils, high ground water tables, wetland within the settlement? | G44: No | H44: =IF(OR(G44=$J$47,G44=$J$48,G44=$J$49),$J$9,$J$8) | I44: =IF(G44=$J$47,$K$47,IF(G44=$J$48,$K$48,$K$49)) -> 1 | J44: Decrease | K44: 1
A45: =A44+1 -> 2 | D45: Impact | E45: Are significant impacts on people attributed to settling in inadequate or risky areas? | F45: Are adverse imacts directly related to risk zones | G45: No | H45: =IF(OR(G45=$J$16,G45=$J$17,G45=$J$18),$J$9,$J$8) | I45: =IF(G45=$J$16,$K$16,IF(G45=$J$17,$K$17,$K$18)) -> 1
A46: =A45+1 -> 3 | D46: Sensitization | E46: Are people settld in sensitive and risky areas aware of the dangers involved in settling there? | F46: Do the settlers know the dangers and precautions? | G46: No | H46: =IF(OR(G46=$J$31,G46=$J$32,G46=$J$33),$J$9,$J$8) | I46: =IF(G46=$J$16,$K$16,IF(G46=$J$17,$K$17,$K$18)) -> 1 | J46: List 8 | K46: yes is bad
J47: Yes | K47: 3
A48: =A47+1 -> 1 | B48: 9 | C48: Other Factors | D48: Fire/wildfires | E48: How frequent are there fires/wild fires experienced in the area that adversely affect the community? | F48: Is the population impacted by fire in and around your area? | G48: Not applicable | H48: =IF(OR(G48=$J$21,G48=$J$22,G48=$J$23),$J$9,$J$8) | I48: =IF(G48=$J$21,$K$21,IF(G48=$J$22,$K$22,$K$23)) -> 1 | J48: Maybe | K48: 2
A49: =A48+1 -> 2 | D49: Lightning | E49: How frequent is there lightning experienced in the area that adversely affects the community? | F49: Is the population impacted by lightening in and around your area? | G49: Not applicable | H49: =IF(OR(G49=$J$21,G49=$J$22,G49=$J$23),$J$9,$J$8) | I49: =IF(G49=$J$21,$K$21,IF(G49=$J$22,$K$22,$K$23)) -> 1 | J49: No | K49: 1
A50: =A49+1 -> 3 | D50: Snow | E50: How frequent is are there hailstorms experienced in the area that adversely affect the community? | F50: Is the population impacted by snowfall in and around your area? | G50: Not applicable | H50: =IF(OR(G50=$J$21,G50=$J$22,G50=$J$23),$J$9,$J$8) | I50: =IF(G50=$J$21,$K$21,IF(G50=$J$22,$K$22,$K$23)) -> 1
A51: =A50+1 -> 4 | D51: Hail | E51: How frequent is are there snowfalls experienced in the area that adversely affect the community? | F51: Is the population impacted by hail in and around your area? | G51: Not applicable | H51: =IF(OR(G51=$J$21,G51=$J$22,G51=$J$23),$J$9,$J$8) | I51: =IF(G51=$J$21,$K$21,IF(G51=$J$22,$K$22,$K$23)) -> 1
A52: =A51+1 -> 5 | D52: EA or VA | E52: How frequent is there earthquakes/volcanic activities experienced in the area that adversely affect the community? | F52: Is the population impacted by earthquakes/volcanic activities in and around your area? | G52: Not applicable | H52: =IF(OR(G52=$J$21,G52=$J$22,G52=$J$23),$J$9,$J$8) | I52: =IF(G52=$J$21,$K$21,IF(G52=$J$22,$K$22,$K$23)) -> 1 | J52: List 9 | K52: yes is bad
A53: =A52+1 -> 6 | D53: Soil Extraction | E53: Are there considerable amounts of soil being extracted in particular locations of the area (e.g. fo brick making etc)? | F53: Consider extraction for building,road construction etc. | G53: No | H53: =IF(OR(G53=$J$47,G53=$J$48,G53=$J$49),$J$9,$J$8) | I53: =IF(G53=$J$47,$K$47,IF(G53=$J$48,$K$48,$K$49)) -> 1 | J53: Yes, but less than 4 days | K53: 1
A54: =A53+1 -> 7 | D54: Deforestation | E54: Is there considerable deforestation taking place in the area/the proximity of the area? | F54: Tree cutting for energy source, construction etc | G54: No | H54: =IF(OR(G54=$J$47,G54=$J$48,G54=$J$49),$J$9,$J$8) | I54: =IF(G54=$J$47,$K$47,IF(G54=$J$48,$K$48,$K$49)) -> 1 | J54: Yes, between 4 days to 14 days | K54: 2
A55: =A54+1 -> 8 | D55: Ubarnization | E55: Is there significant urbanisatiotn taking place in the area? | F55: Increasing the built up area and impermeable surfaces ? | G55: No | H55: =IF(OR(G55=$J$47,G55=$J$48,G55=$J$49),$J$9,$J$8) | I55: =IF(G55=$J$47,$K$47,IF(G55=$J$48,$K$48,$K$49)) -> 1 | J55: Yes, at least 14 days | K55: 3
J57: List 10 | K57: Whole is bad
J58: Entirely | K58: 3
J59: About half | K59: 2
J60: Less than half | K60: 1

Sheet Exposure
F7: NOTE: ONCE YOU CLICK THIS BUTTON YOU CANNOT UNDO YOUR ACTIONS
B8: CURRENT EXPOSURE | J8: No Selecton Done!
J9: =""
B10: Exposure | E10: Question | F10: Comments/Description | G10: Answer? | H10: Add Note On Each Answer | I10: Rating? | J10: List 1 | K10: yes is bad
A11: 1 | B11: 1 | C11: Livelihoods | D11: Food Security | E11: Do the actual climatic conditions noticeably impact the food production output? | F11: Consider food security at different at different times of the year (i.e. rainy season)? | G11: Not noticed | H11: =IF(OR(G11=$J$11,G11=$J$12,G11=$J$13),$J$9,$J$8) | I11: =IF(G11=$J$11,$K$11,IF(G11=$J$12,$K$12,$K$13)) -> 1 | J11: Severely and often | K11: 3
A12: =A4+1 -> 1 | D12: Grazing/Farm Land | E12: Is grazing land and / or farmland affected by the climate and / or inadequate land use | F12: Consider continued availability of sufficient gras for grazing | G12: Not noticed | H12: =IF(OR(G12=$J$11,G12=$J$12,G12=$J$13),$J$9,$J$8) | I12: =IF(G12=$J$11,$K$11,IF(G12=$J$12,$K$12,$K$13)) -> 1 | J12: Severely and not often | K12: 2
A13: =A5+1 -> 1 | D13: Crops | E13: Are crops adversely impacted by the climate, e.g. by drought, hale, landslides, flooding etc? | F13: Consider protection of crops in view of climate and weather related events | G13: Not noticed | H13: =IF(OR(G13=$J$11,G13=$J$12,G13=$J$13),$J$9,$J$8) | I13: =IF(G13=$J$11,$K$11,IF(G13=$J$12,$K$12,$K$13)) -> 1 | J13: Not noticed | K13: 1
A14: =A3+1 -> 1 | D14: Livestock | E14: Is livestock adversely impacted by the changing climate and severe weather events or by environmental pollution? | F14: Consider capability to maintain health and safety of livestock | G14: Not noticed | H14: =IF(OR(G14=$J$11,G14=$J$12,G14=$J$13),$J$9,$J$8) | I14: =IF(G14=$J$11,$K$11,IF(G14=$J$12,$K$12,$K$13)) -> 1
A15: =A4+1 -> 1 | D15: Fishstock | E15: Is fishstock depleting by the changing climate and severe weather events, ocean warming or environmental pollution? | F15: Consider health and continued availability of fishstock | G15: Not noticed | H15: =IF(OR(G15=$J$11,G15=$J$12,G15=$J$13),$J$9,$J$8) | I15: =IF(G15=$J$11,$K$11,IF(G15=$J$12,$K$12,$K$13)) -> 1
A16: =A5+1 -> 1 | D16: Local commerce | E16: Are floods/extreme temperatures/water shortages noticeably affecting business success? | F16: Consider resilience of SME's | G16: Not noticed | H16: =IF(OR(G16=$J$11,G16=$J$12,G16=$J$13),$J$9,$J$8) | I16: =IF(G16=$J$11,$K$11,IF(G16=$J$12,$K$12,$K$13)) -> 1 | J16: List 2 | K16: yes is bad
A17: =A7+1 -> 1 | D17: Gender | E17: Are men and women equally adversely impacted (if impacted at all) by the challenges resulting from changing climate? | F17: Consider effects of changung climate on gender based activity | G17: Equally affected | H17: =IF(OR(G17=$J$17,G17=$J$18,G17=$J$19),$J$9,$J$8) | I17: =IF(G17=$J$17,$K$17,IF(G17=$J$18,$K$18,$K$19)) -> 1 | J17: Equally affected | K17: 1
A18: =A8+1 -> 1 | D18: Conviviality | E18: Are peace and conviviality adversely impacted due to the challenges resulting from changing climate? | F18: Consider peace in the community | G18: Not noticed | H18: =IF(OR(G18=$J$11,G18=$J$12,G18=$J$13),$J$9,$J$8) | I18: =IF(G18=$J$11,$K$11,IF(G18=$J$12,$K$12,$K$13)) -> 1 | J18: Women more affected | K18: 2
A19: =A9+1 -> 1 | D19: Education | E19: Is there any effeects on the regularity of education cthat result from changing climate and severe weather evants? | F19: Consider continued access to education independent from climate and weather events | G19: No change noticed | H19: =IF(OR(G19=$J$22,G19=$J$23,G19=$J$24),$J$9,$J$8) | I19: =IF(G19=$J$22,$K$22,IF(G19=$J$23,$K$23,$K$24)) -> 1 | J19: Men more affected | K19: 3
A20: =A10+1 -> 1 | D20: WFI/WFDU | E20: Is water availability for uses other than human consumption adversely affected by changing climate and sevee weather events? | F20: Consider access to water for household uses and irrigation | G20: Not noticed | H20: =IF(OR(G20=$J$11,G20=$J$12,G20=$J$13),$J$9,$J$8) | I20: =IF(G20=$J$11,$K$11,IF(G20=$J$12,$K$12,$K$13)) -> 1
A21: =A11+1 -> 2 | D21: ATF/I | E21: Is household financial demand increasing due to the challenges resulting fom changing climate and severe weather events? | F21: Consider changing financial needs due to climate and weather events | G21: Not Noticed | H21: =IF(OR(G21=$J$27,G21=$J$28,G21=$J$29),$J$9,$J$8) | I21: =IF(G21=$J$27,$K$27,IF(G21=$J$28,$K$28,$K$29)) -> 1 | J21: List 3 | K21: Highly is bad
A22: =A21+1 -> 3 | D22: Disaster Events | E22: Have climate related and extreme weather events caused disasters/emergencies that affected the community before | F22: This includes impacts from temperature, rainfall, droughts and/or floods | G22: Not noticed | H22: =IF(OR(G22=$J$11,G22=$J$12,G22=$J$13),$J$9,$J$8) | I22: =IF(G22=$J$11,$K$11,IF(G22=$J$12,$K$12,$K$13)) -> 1 | J22: Regularity highly affected | K22: 3
I23: ="" | J23: Regularity not often disrupted | K23: 2
A24: =A22+1 -> 4 | B24: 2 | C24: Health & Safety | D24: Borne Diseases | E24: Have climate related events and conditions affected larger portions of the community with diseases? | F24: Water-borne diseases include typhoid fever, cholera, leptospirosis and hepatitis A; Vector diseases include malaria, dengue fever, yellow fever, and West Nile Fever | G24: Not noticed | H24: =IF(OR(G24=$J$11,G24=$J$12,G24=$J$13),$J$9,$J$8) | I24: =IF(G24=$J$11,$K$11,IF(G24=$J$12,$K$12,$K$13)) -> 1 | J24: No change noticed | K24: 1
A25: =A21+1 -> 3 | D25: SLUP&C | E25: Have climate related events increased risky conditions for large portions of the community based on their location ? | F25: Consider changes to the safety of housing locations | G25: Not noticed | H25: =IF(OR(G25=$J$11,G25=$J$12,G25=$J$13),$J$9,$J$8) | I25: =IF(G25=$J$11,$K$11,IF(G25=$J$12,$K$12,$K$13)) -> 1
A26: =A22+1 -> 4 | D26: SWM | E26: Is solid waste dumped in uncontrolled manner and locations ? | F26: Consider inconsiderate depositing of solid waste in the public real, inside drainages, manholes, etc | G26: Negligible | H26: =IF(OR(G26=$J$33,G26=$J$34,G26=$J$35),$J$9,$J$8) | I26: =IF(G26=$J$33,$K$33,IF(G26=$J$34,$K$34,$K$35)) -> 1 | J26: List 4 | K26: Largely is bad
A27: =A23+1 -> 1 | D27: LWM | E27: Is liquid waste deposited in uncontrolled manner and locations ? | F27: Consider grey water discharge and open defecatio in the public realm | G27: Negligible | H27: =IF(OR(G27=$J$33,G27=$J$34,G27=$J$35),$J$9,$J$8) | I27: =IF(G27=$J$33,$K$33,IF(G27=$J$34,$K$34,$K$35)) -> 1 | J27: Largely affected | K27: 3
A28: =A24+1 -> 5 | D28: ATHS | E28: Are there adequate health services accessible within the location and to every household? | F28: Consider accessibility, staffing, and quality of health facilities and services | G28: Yes | H28: =IF(OR(G28=$J$38,G28=$J$39,G28=$J$40),$J$9,$J$8) | I28: =IF(G28=$J$38,$K$38,IF(G28=$J$39,$K$39,$K$40)) -> 1 | J28: Not much affected | K28: 2
A29: =A28+1 -> 6 | D29: ATHE | E29: Is the general settlement environment (air, water, soil, etc) perceived as healthy and intact? | F29: Consider perceived cleanliness of air, water and soils, and any measurements of pollution as available | G29: Yes | H29: =IF(OR(G29=$J$38,G29=$J$39,G29=$J$40),$J$9,$J$8) | I29: =IF(G29=$J$38,$K$38,IF(G29=$J$39,$K$39,$K$40)) -> 1 | J29: Not Noticed | K29: 1
I30: =""
A31: =A29+1 -> 7 | B31: 3 | C31: Assets and Utilities | D31: Housing | E31: Are climate related events affecting the safety of homes | F31: Consider changes to the safety of housing structures | G31: Not noticed | H31: =IF(OR(G31=$J$11,G31=$J$12,G31=$J$13),$J$9,$J$8) | I31: =IF(G31=$J$11,$K$11,IF(G31=$J$12,$K$12,$K$13)) -> 1
A32: =A22+1 -> 4 | D32: Public facilities | E32: Are public community facilities impacted by climate hazards | F32: This includes critical facilities, particularly health facilities, schools and essential community services | G32: Not noticed | H32: =IF(OR(G32=$J$11,G32=$J$12,G32=$J$13),$J$9,$J$8) | I32: =IF(G32=$J$11,$K$11,IF(G32=$J$12,$K$12,$K$13)) -> 1 | J32: List 5 | K32: Largely is bad
A33: =A32+1 -> 5 | D33: SWD | E33: Is there absence of functional constructed storm water drainage channels? | F33: This refers to constructed drainages and natural or constructed infiltration areas | G33: Negligible | H33: =IF(OR(G33=$J$33,G33=$J$34,G33=$J$35),$J$9,$J$8) | I33: =IF(G33=$J$33,$K$33,IF(G33=$J$34,$K$34,$K$35)) -> 1 | J33: Predominantly | K33: 3
A34: =A33+1 -> 6 | D34: Sanitary facilities | E34: Are pit latrines and / or open defecation the primary sanitation mode? | F34: This is specific to household sanitation | G34: Negligible | H34: =IF(OR(G34=$J$33,G34=$J$34,G34=$J$35),$J$9,$J$8) | I34: =IF(G34=$J$33,$K$33,IF(G34=$J$34,$K$34,$K$35)) -> 1 | J34: Partially | K34: 2
A35: =A25+1 -> 4 | D35: Sewer lines | E35: Are sewers absent, dysfunctional, exposed to floods, or households not connected? | F35: This refers to the functionality of sewer lines, if any | G35: Negligible | H35: =IF(OR(G35=$J$33,G35=$J$34,G35=$J$35),$J$9,$J$8) | I35: =IF(G35=$J$33,$K$33,IF(G35=$J$34,$K$34,$K$35)) -> 1 | J35: Negligible | K35: 1
A36: =A28+1 -> 6 | D36: Power lines/supply | E36: Is power supply infrastructure exposed to extreme weather events (overhead power lines, location in flood plains etc), or located underground nearby soil extraction areas | F36: This refers to the design and location of power lines to judge its resiliency | G36: Negligible | H36: =IF(OR(G36=$J$33,G36=$J$34,G36=$J$35),$J$9,$J$8) | I36: =IF(G36=$J$33,$K$33,IF(G36=$J$34,$K$34,$K$35)) -> 1
A37: =A36+1 -> 7 | D37: Energy for HH use | E37: Is there access to electricity at HH level | F37: This refers to the prevalent use of charcoal and wood | G37: Negligible | H37: =IF(OR(G37=$J$33,G37=$J$34,G37=$J$35),$J$9,$J$8) | I37: =IF(G37=$J$33,$K$33,IF(G37=$J$34,$K$34,$K$35)) -> 1 | J37: List 6 | K37: No is bad
A38: =A37+1 -> 8 | D38: Water pipes | E38: Are there (functional) water pipes in the settlement ? | F38: This is about availability of piped water supply network | G38: Negligible | H38: =IF(OR(G38=$J$33,G38=$J$34,G38=$J$35),$J$9,$J$8) | I38: =IF(G38=$J$33,$K$33,IF(G38=$J$34,$K$34,$K$35)) -> 1 | J38: Yes | K38: 1
A39: =A38+1 -> 9 | D39: PWT | E39: Have functionality or reliability of potable water treatment facilities serving the area been impacted by climate hazards? | F39: Consider location and protection of water storage of any | G39: Not noticed | H39: =IF(OR(G39=$J$11,G39=$J$12,G39=$J$13),$J$9,$J$8) | I39: =IF(G39=$J$11,$K$11,IF(G39=$J$12,$K$12,$K$13)) -> 1 | J39: Maybe | K39: 2
A40: =A39+1 -> 10 | D40: Water Storage | E40: Is water storage safely located and protected or is water storage impacted by climate events? | F40: Consider location and protection of water teatment facilities relevant to the water supply of the area | G40: Not noticed | H40: =IF(OR(G40=$J$11,G40=$J$12,G40=$J$13),$J$9,$J$8) | I40: =IF(G40=$J$11,$K$11,IF(G40=$J$12,$K$12,$K$13)) -> 1 | J40: No | K40: 3
A41: =A40+1 -> 11 | D41: R & T | E41: Are accessibility / mobility compromised during extreme weather events and roads and transport infrastructure impacted by floods, land slides, high temperaturs, or other climate-induced events? | F41: Consider all weather access to households and critical facilities | G41: Not noticed | H41: =IF(OR(G41=$J$11,G41=$J$12,G41=$J$13),$J$9,$J$8) | I41: =IF(G41=$J$11,$K$11,IF(G41=$J$12,$K$12,$K$13)) -> 1
A42: =A41+1 -> 12 | D42: Communication | E42: Is communication infrastructure in the settlement (fiber optic cables, wireless hotspots, etc) safely located and protected, if any | F42: Consider location and protection of critical commuication infrastructure | G42: Yes | H42: =IF(OR(G42=$J$38,G42=$J$39,G42=$J$40),$J$9,$J$8) | I42: =IF(G42=$J$38,$K$38,IF(G42=$J$39,$K$39,$K$40)) -> 1 | J42: List 7 | K42: Clay is bad
I43: ="" | J43: Clay | K43: 3
A44: =A43+1 -> 1 | B44: 4 | C44: Potable water | D44: Access | E44: Is potable water accessible at all times, or scarcities often being faced? | F44: This refers to water needed for drinking, its safety and quantity | G44: Negligible | H44: =IF(OR(G44=$J$33,G44=$J$34,G44=$J$35),$J$9,$J$8) | I44: =IF(G44=$J$33,$K$33,IF(G44=$J$34,$K$34,$K$35)) -> 1 | J44: Sand | K44: 2
A45: =A44+1 -> 2 | D45: Scarcities | E45: is potable water access impacted by severe climate related events, e.g. flooding, drought? | F45: This refers to water needed for drinking, its safety and quantity | G45: Not noticed | H45: =IF(OR(G45=$J$11,G45=$J$12,G45=$J$13),$J$9,$J$8) | I45: =IF(G45=$J$11,$K$11,IF(G45=$J$12,$K$12,$K$13)) -> 1 | J45: Loam | K45: 1
A46: =A45+1 -> 3 | D46: Quality | E46: Is the quality of the potable water accessible to the community adequate | F46: This refers to water needed for drinking, its safety and quantity | G46: Yes | H46: =IF(OR(G46=$J$38,G46=$J$39,G46=$J$40),$J$9,$J$8) | I46: =IF(G46=$J$38,$K$38,IF(G46=$J$39,$K$39,$K$40)) -> 1
I47: ="" | J47: List 8 | K47: Yes is bad
A48: =A47+1 -> 1 | B48: 5 | C48: EBS | D48: Soil | E48: Is the commuity settling on sandy or clayey soils? | F48: Both types of soils pose risks depending on the topography ad weather events | G48: Loam | H48: =IF(OR(G48=$J$43,G48=$J$44,G48=$J$45),$J$9,$J$8) | I48: =IF(G48=$J$43,$K$43,IF(G48=$J$44,$K$44,$K$45)) -> 1 | J48: Yes | K48: 3
A49: =A48+1 -> 2 | D49: LC & P | E49: Are there adequate natural areas where water infiltration is enabled, and the amounts of surface runoff that is not infiltrating and not increasing? | F49: Consider natural infiltration areas and capacities | G49: Yes | H49: =IF(OR(G49=$J$38,G49=$J$39,G49=$J$40),$J$9,$J$8) | I49: =IF(G49=$J$38,$K$38,IF(G49=$J$39,$K$39,$K$40)) -> 1 | J49: No | K49: 2
A50: =A49+1 -> 3 | D50: NV | E50: Is there mature natural vegetation in the area and is the vegetative cover well conserved to not reduce ? | F50: Consider noticeable changes to vegetative cover | G50: Yes | H50: =IF(OR(G50=$J$38,G50=$J$39,G50=$J$40),$J$9,$J$8) | I50: =IF(G50=$J$38,$K$38,IF(G50=$J$39,$K$39,$K$40)) -> 1 | J50: Not noticed | K50: 1
A51: =A50+1 -> 4 | D51: Wetland | E51: Are natural wetlands being respected and kept clean and unbuilt/preserved, and not disturbed by inadequate uses? | F51: Consider maintained functionality of wetlands | G51: Yes | H51: =IF(OR(G51=$J$38,G51=$J$39,G51=$J$40),$J$9,$J$8) | I51: =IF(G51=$J$38,$K$38,IF(G51=$J$39,$K$39,$K$40)) -> 1
A52: =A51+1 -> 5 | D52: Biodiversity | E52: Are there green corridors allowing uncostrained passege of wild animals outside of the settlement? | F52: Consider noticeable changes to biodiversity | G52: Yes | H52: =IF(OR(G52=$J$38,G52=$J$39,G52=$J$40),$J$9,$J$8) | I52: =IF(G52=$J$38,$K$38,IF(G52=$J$39,$K$39,$K$40)) -> 1 | J52: List 9 | K52: Largely is bad
A53: =A52+1 -> 6 | D53: NWB | E53: Is the settlement located in proximity to a water body and do households settle within the riperian corridor? | F53: Consider respect to the natural seasonal changes of the water body | G53: Yes | H53: =IF(OR(G53=$J$38,G53=$J$39,G53=$J$40),$J$9,$J$8) | I53: =IF(G53=$J$38,$K$38,IF(G53=$J$39,$K$39,$K$40)) -> 1 | J53: Largely | K53: 3
A54: =A53+1 -> 7 | D54: Sea | E54: Is the sea level increasing? | F54: Consider noticeable changes to sea level | G54: Unknown | H54: =IF(OR(G54=$J$63,G54=$J$64,G54=$J$65),$J$9,$J$8) | I54: =IF(G54=$J$63,$K$63,IF(G54=$J$64,$K$64,$K$65)) -> 1 | J54: Partially | K54: 2
A55: =A54+1 -> 8 | D55: EF | E55: Is inadequate land use causing environmental and land degradation? Is there risk of environmental contamination from release of hazardous substances during extreme weather events | F55: Consider unmitigated release of hazardous substances | G55: No | H55: =IF(OR(G55=$J$68,G55=$J$69,G55=$J$70),$J$9,$J$8) | I55: =IF(G55=$J$73,$K$73,IF(G55=$J$74,$K$74,$K$75)) -> 1 | J55: Not noticed | K55: 1
A56: =A55+1 -> 9 | D56: Land use | E56: Is construction taking place in hazardous / risky areas or are land use sensitivities respected | F56: Consider respect to risk areas | G56: No | H56: =IF(OR(G56=$J$68,G56=$J$69,G56=$J$70),$J$9,$J$8) | I56: =IF(G56=$J$73,$K$73,IF(G56=$J$74,$K$74,$K$75)) -> 1
A57: =A56+1 -> 10 | D57: Topography | E57: Is the settlement located on steep terrain? | F57: Consider respect to risk areas | G57: No | H57: =IF(OR(G57=$J$68,G57=$J$69,G57=$J$70),$J$9,$J$8) | I57: =IF(G57=$J$73,$K$73,IF(G57=$J$74,$K$74,$K$75)) -> 1 | J57: List 10 | K57: Usually is bad
I58: ="" | J58: Usually | K58: 3
A59: =A58+1 -> 1 | B59: 6 | C59: Institutions | D59: EWS | E59: Is there a functional early warning system/mechanim/arrangement to warn the community about disaster risks? | F59: Consider EWS, evacuation plans and awareess | G59: No | H59: =IF(OR(G59=$J$38,G59=$J$39,G59=$J$40),$J$9,$J$8) | I59: =IF(G59=$J$73,$K$73,IF(G59=$J$74,$K$74,$K$75)) -> 1 | J59: Sometimes | K59: 2
A60: =A59+1 -> 2 | D60: A & I | E60: Are extreme weather events affeecting the communities by surprise? | F60: Consider access to weather information and warning | G60: No | H60: =IF(OR(G60=$J$68,G60=$J$69,G60=$J$70),$J$9,$J$8) | I60: =IF(G60=$J$73,$K$73,IF(G60=$J$74,$K$74,$K$75)) -> 1 | J60: Never | K60: 1
A61: =A60+1 -> 3 | D61: EC | E61: Is there regular interaction between the community and the county government? | F61: Consider communication mechanisms and frequencies | G61: No | H61: =IF(OR(G61=$J$38,G61=$J$39,G61=$J$40),$J$9,$J$8) | I61: =IF(G61=$J$73,$K$73,IF(G61=$J$74,$K$74,$K$75)) -> 1
A62: =A61+1 -> 4 | D62: R/RP | E62: Is the community considered in county governance and finances budgeted to ensure public responsibilities of the county in the settlement location? | F62: Consider reflection of priorities in CIDP's | G62: No | H62: =IF(OR(G62=$J$38,G62=$J$39,G62=$J$40),$J$9,$J$8) | I62: =IF(G62=$J$73,$K$73,IF(G62=$J$74,$K$74,$K$75)) -> 1 | J62: List 11 | K62: Yes is bad
A63: =A62+1 -> 5 | D63: HFO | E63: Are there adequate health facilities, with adequate personell, equipment and materials ? | F63: Consider access to health facilities and adequate sevices | G63: No | H63: =IF(OR(G63=$J$38,G63=$J$39,G63=$J$40),$J$9,$J$8) | I63: =IF(G63=$J$73,$K$73,IF(G63=$J$74,$K$74,$K$75)) -> 1 | J63: Yes | K63: 3
A64: =A63+1 -> 6 | D64: DP | E64: Are the locations of all critical infrastructure identified and measures in place to protect it? | F64: Consider DRM plans, evacuation plans and awareness | G64: No | H64: =IF(OR(G64=$J$38,G64=$J$39,G64=$J$40),$J$9,$J$8) | I64: =IF(G64=$J$73,$K$73,IF(G64=$J$74,$K$74,$K$75)) -> 1 | J64: No | K64: 2
A65: =A64+1 -> 7 | D65: DR | E65: Are disaster response measures planned and budgeted for and food, water and hygiene predispositioned? | F65: Consider DRM plans and budgets | G65: No | H65: =IF(OR(G65=$J$38,G65=$J$39,G65=$J$40),$J$9,$J$8) | I65: =IF(G65=$J$73,$K$73,IF(G65=$J$74,$K$74,$K$75)) -> 1 | J65: Unknown | K65: 1
A66: =A65+1 -> 8 | D66: PFR | E66: Are recovey finances budgeted for? | F66: Consider recovery budgets | G66: No | H66: =IF(OR(G66=$J$38,G66=$J$39,G66=$J$40),$J$9,$J$8) | I66: =IF(G66=$J$73,$K$73,IF(G66=$J$74,$K$74,$K$75)) -> 1
A67: =A66+1 -> 9 | D67: PFM | E67: Is maintenance and repair of public infrastructures institutionalised and are the responsibilities clear? | F67: Consider functionality of maintenance | G67: No | H67: =IF(OR(G67=$J$38,G67=$J$39,G67=$J$40),$J$9,$J$8) | I67: =IF(G67=$J$73,$K$73,IF(G67=$J$74,$K$74,$K$75)) -> 1 | J67: List 12 | K67: No is bad
J68: Yes | K68: 1
J69: Maybe | K69: 2
J70: No | K70: 3
J72: List 12 | K72: No is bad
J73: Yes | K73: 3
J74: Maybe | K74: 2
E75: s | J75: No | K75: 1

Sheet Sensitivity
F7: NOTE: ONCE YOU CLICK THIS BUTTON YOU CANNOT UNDO YOUR ACTIONS
B8: CURRENT SENSITIVITY | J8: No Selecton Done!
J9: =""
B10: Sensitivity | E10: Question | F10: Comments/Description | G10: Answer? | H10: Add Note On Each Answer | I10: Rating? | J10: List 1 | K10: yes is bad
A11: 1 | B11: 1 | C11: Livelihoods | D11: Food Security | E11: Are access and cost of food changing with extreme weather events? | F11: Consider food security at different at different times of the year (i.e. rainy season)? | G11: Not noticed | H11: =IF(OR(G11=$J$11,G11=$J$12,G11=$J$13),$J$9,$J$8) | I11: =IF(G11=$J$11,$K$11,IF(G11=$J$12,$K$12,$K$13)) -> 1 | J11: Severely and often | K11: 3
A12: =A4+1 -> 1 | D12: Grazing/Farm Land | E12: Is grazing land getting scarcer or more distant | F12: Consider availability of pasture to feed livestock | G12: No | H12: =IF(OR(G12=$J$63,G12=$J$64,G12=$J$65),$J$9,$J$8) | I12: =IF(G12=$J$63,$K$63,IF(G12=$J$64,$K$64,$K$65)) -> 1 | J12: Severely and not often | K12: 2
A13: =A5+1 -> 1 | D13: Crops | E13: Are most households dependent on subsistance farming (crops) for food (not buying)? | F13: Consider dependency on subsistence agriculture for majority of households | G13: Low Dependancy | H13: =IF(OR(G13=$J$17,G13=$J$18,G13=$J$19),$J$9,$J$8) | I13: =IF(G13=$J$17,$K$17,IF(G13=$J$18,$K$18,$K$19)) -> 1 | J13: Not noticed | K13: 1
A14: =A3+1 -> 1 | D14: Livestock | E14: Are most households dependent on own livestock for food (not buying)? | F14: Consider dependency on own livestock keeping for majority of households | G14: Low Dependancy | H14: =IF(OR(G14=$J$17,G14=$J$18,G14=$J$19),$J$9,$J$8) | I14: =IF(G14=$J$17,$K$17,IF(G14=$J$18,$K$18,$K$19)) -> 1
A15: =A4+1 -> 1 | D15: Fishstock | E15: Are most households dependent on fishing for food (not buying)? | F15: Consider dependency on fishing for majority of households | G15: Low Dependancy | H15: =IF(OR(G15=$J$17,G15=$J$18,G15=$J$19),$J$9,$J$8) | I15: =IF(G15=$J$17,$K$17,IF(G15=$J$18,$K$18,$K$19)) -> 1
A16: =A5+1 -> 1 | D16: Local commerce | E16: Are extreme weather events interrupting secure livelihood, business and incomes for large portions of the communityand lead to economically precarious situations ? | F16: Consider dependency on economic activities that are sensitive to climate hazards and severe weather | G16: Low Dependancy | H16: =IF(OR(G16=$J$17,G16=$J$18,G16=$J$19),$J$9,$J$8) | I16: =IF(G16=$J$17,$K$17,IF(G16=$J$18,$K$18,$K$19)) -> 1 | J16: List 2 | K16: yes is bad
A17: =A7+1 -> 1 | D17: Gender | E17: Are women highly dependent on undertaking business inside the settlement? | F17: Consider location of the income generaing activity and sensitivity to climae related hazard | G17: Low Dependancy | H17: =IF(OR(G17=$J$17,G17=$J$18,G17=$J$19),$J$9,$J$8) | I17: =IF(G17=$J$17,$K$17,IF(G17=$J$18,$K$18,$K$19)) -> 1 | J17: Most Residents Concerned | K17: 3
A18: =A8+1 -> 1 | D18: Conviviality | E18: Do resource scarcities that result from cilmate related events or conditions frequently lead to conflicts within the community/or with other communities? | F18: Consider conflict and dispute raised due to climate related hazards | G18: Not noticed | H18: =IF(OR(G18=$J$22,G18=$J$23,G18=$J$24),$J$9,$J$8) | I18: =IF(G18=$J$22,$K$22,IF(G18=$J$23,$K$23,$K$24)) -> 1 | J18: Half Residents Concerned | K18: 2
A19: =A9+1 -> 1 | D19: Education | E19: Are large percentages of children frequently unable to reach/attend school due to climate related and severe weather events? | F19: Consider dependency of education services on climate conditions | G19: Low Dependancy | H19: =IF(OR(G19=$J$17,G19=$J$18,G19=$J$19),$J$9,$J$8) | I19: =IF(G19=$J$17,$K$17,IF(G19=$J$18,$K$18,$K$19)) -> 1 | J19: Low Dependancy | K19: 1
A20: =A10+1 -> 1 | D20: WFI/WFDU | E20: Are there water scarcities often being faced that negatively impact farming, livestock keeping and business? | F20: Consider dependency of access to water on climate conditions | G20: Not noticed | H20: =IF(OR(G20=$J$22,G20=$J$23,G20=$J$24),$J$9,$J$8) | I20: =IF(G20=$J$22,$K$22,IF(G20=$J$23,$K$23,$K$24)) -> 1
A21: =A11+1 -> 2 | D21: ATF/I | E21: Does the community have access to financial services, health insurance and disaster risk insurance? | F21: Consider financial buffers for periods of interrupted income or effects on health | G21: Almost Nobody Has | H21: =IF(OR(G21=$J$27,G21=$J$28,G21=$J$29),$J$9,$J$8) | I21: =IF(G21=$J$27,$K$27,IF(G21=$J$28,$K$28,$K$29)) -> 1 | J21: List 3 | K21: Severe is bad
D22: Disaster Events | E22: How would the impact of climate related disaster be rated, if it were to occur ? | F22: This includes impacts from temperature, rainfall, droughts and/or floods | G22: Not noticed | H22: =IF(OR(G22=$J$53,G22=$J$54,G22=$J$55),$J$9,$J$8) | I22: =IF(G22=$J$53,$K$53,IF(G22=$J$54,$K$54,$K$55)) -> 1 | J22: Severe Problem | K22: 3
J23: Still Okay | K23: 2
A24: =A22+1 -> 1 | B24: 2 | C24: Health & Safety | D24: Borne Diseases | E24: Are health incidences increasing and may be related to the impact of changing extreme weather events? | F24: Compare in relation to the past | G24: Few Residents Concerned | H24: =IF(OR(G24=$J$33,G24=$J$34,G24=$J$35),$J$9,$J$8) | I24: =IF(G24=$J$33,$K$33,IF(G24=$J$34,$K$34,$K$35)) -> 1 | J24: Not noticed | K24: 1
A25: =A21+1 -> 3 | D25: SLUP&C | E25: Are safety incidences increasing and may be related to the impact of changes of extreme weather events? | F25: Compare in relation to the past | G25: Few Residents Concerned | H25: =IF(OR(G25=$J$33,G25=$J$34,G25=$J$35),$J$9,$J$8) | I25: =IF(G25=$J$33,$K$33,IF(G25=$J$34,$K$34,$K$35)) -> 1
A26: =A22+1 -> 1 | D26: SWM | E26: Is solid waste adequately managed, and unmanaged waste is not increasing the adverse impacts of severe weather events ? | F26: Consider mitigation efforts for solid waste not to block drainages and water infiltraion capacities | G26: Yes | H26: =IF(OR(G26=$J$43,G26=$J$44,G26=$J$45),$J$9,$J$8) | I26: =IF(G26=$J$43,$K$43,IF(G26=$J$44,$K$44,$K$45)) -> 1 | J26: List 4 | K26: Largely is bad
A27: =A23+1 -> 1 | D27: LWM | E27: Is untreated waste water released into the environment from industries or domestic uses ? | F27: Consider floodwaters mobilizing faecal sludges and other pollutants | G27: Not noticed | H27: =IF(OR(G27=$J$22,G27=$J$23,G27=$J$24),$J$9,$J$8) | I27: =IF(G27=$J$22,$K$22,IF(G27=$J$23,$K$23,$K$24)) -> 1 | J27: Most Residents Have | K27: 3
A28: =A24+1 -> 2 | D28: ATHS | E28: Are health services inaccessible or dysfunctional during climate related and severe weather events? | F28: Consider uninterrupted health services | G28: Not noticed | H28: =IF(OR(G28=$J$22,G28=$J$23,G28=$J$24),$J$9,$J$8) | I28: =IF(G28=$J$22,$K$22,IF(G28=$J$23,$K$23,$K$24)) -> 1 | J28: Half Residents Have | K28: 2
A29: =A28+1 -> 3 | D29: ATHE | E29: Are there common sources of pollution that originate from human activity? | F29: Consider prevalence of use of biomass for cooking, waste burning and indoor use of pesticides, and industrial pollution | G29: Not noticed | H29: =IF(OR(G29=$J$22,G29=$J$23,G29=$J$24),$J$9,$J$8) | I29: =IF(G29=$J$22,$K$22,IF(G29=$J$23,$K$23,$K$24)) -> 1 | J29: Almost Nobody Has | K29: 1
A31: =A29+1 -> 4 | B31: 3 | C31: Assets and Utilities | D31: Housing | E31: Are foundations stable, walls protected from moisture and roof fixtures adequate? | F31: Consider protection of biult structures | G31: Not noticed | H31: =IF(OR(G31=$J$22,G31=$J$23,G31=$J$24),$J$9,$J$8) | I31: =IF(G31=$J$22,$K$22,IF(G31=$J$23,$K$23,$K$24)) -> 1
A32: =A22+1 -> 1 | D32: Public facilities | E32: Are public facilities inaccessible or dysfunctional due to climate related and severe weather events? | F32: Consider all weather accessibility and operations of public services | G32: Not noticed | H32: =IF(OR(G32=$J$22,G32=$J$23,G32=$J$24),$J$9,$J$8) | I32: =IF(G32=$J$22,$K$22,IF(G32=$J$23,$K$23,$K$24)) -> 1 | J32: List 5 | K32: Largely is bad
A33: =A32+1 -> 2 | D33: SWD | E33: Are drainages under-dimensioned or incomplete? | F33: Consider drainage overflows or faulty outlet designs | G33: Not noticed | H33: =IF(OR(G33=$J$22,G33=$J$23,G33=$J$24),$J$9,$J$8) | I33: =IF(G33=$J$22,$K$22,IF(G33=$J$23,$K$23,$K$24)) -> 1 | J33: Most Residents Concerned | K33: 3
A34: =A33+1 -> 3 | D34: Sanitary facilities | E34: Are sanitation facilities often submerged in water and feaces carried by flood and storm water ? | F34: This is specific to household sanitation | G34: Not noticed | H34: =IF(OR(G34=$J$22,G34=$J$23,G34=$J$24),$J$9,$J$8) | I34: =IF(G34=$J$22,$K$22,IF(G34=$J$23,$K$23,$K$24)) -> 1 | J34: Half Residents Concerned | K34: 2
A35: =A25+1 -> 4 | D35: Sewer lines | E35: Are there sewer lines existing, which are however under-dimensioned (overflowing) or stagnant (e.g. from water shortage)? | F35: Assess functionality of sewers if any | G35: Not noticed | H35: =IF(OR(G35=$J$22,G35=$J$23,G35=$J$24),$J$9,$J$8) | I35: =IF(G35=$J$22,$K$22,IF(G35=$J$23,$K$23,$K$24)) -> 1 | J35: Few Residents Concerned | K35: 1
A36: =A28+1 -> 3 | D36: Power lines/supply | E36: is energy supply regularly impacted / interrupted in relation to extreme weather events? | F36: Consider reliability of power supply from grid | G36: Not noticed | H36: =IF(OR(G36=$J$22,G36=$J$23,G36=$J$24),$J$9,$J$8) | I36: =IF(G36=$J$22,$K$22,IF(G36=$J$23,$K$23,$K$24)) -> 1
A37: =A36+1 -> 4 | D37: Energy for HH use | E37: Do most HHs depend on biomass for cooking | F37: Consider household connections and reliability of supply | G37: Not noticed | H37: =IF(OR(G37=$J$22,G37=$J$23,G37=$J$24),$J$9,$J$8) | I37: =IF(G37=$J$22,$K$22,IF(G37=$J$23,$K$23,$K$24)) -> 1 | J37: List 6 | K37: No is bad
A38: =A37+1 -> 5 | D38: Water pipes | E38: are water pipes functional during and after extreme weather events? | F38: Consider resiliency of water pipes network | G38: Not noticed | H38: =IF(OR(G38=$J$22,G38=$J$23,G38=$J$24),$J$9,$J$8) | I38: =IF(G38=$J$22,$K$22,IF(G38=$J$23,$K$23,$K$24)) -> 1 | J38: Largely | K38: 3
A39: =A38+1 -> 6 | D39: PWT | E39: is water treatment of piped water ensured at all times ? | F39: Consider safety of piped water | G39: Not noticed | H39: =IF(OR(G39=$J$22,G39=$J$23,G39=$J$24),$J$9,$J$8) | I39: =IF(G39=$J$22,$K$22,IF(G39=$J$23,$K$23,$K$24)) -> 1 | J39: Moderate | K39: 2
A40: =A39+1 -> 7 | D40: Water Storage | E40: Does the community rely on water storage infrastructure | F40: Consider use of water storage to bridge unreliable supply | G40: Not noticed | H40: =IF(OR(G40=$J$53,G40=$J$54,G40=$J$55),$J$9,$J$8) | I40: =IF(G40=$J$53,$K$53,IF(G40=$J$54,$K$54,$K$55)) -> 1 | J40: Partially | K40: 1
A41: =A40+1 -> 8 | D41: R & T | E41: Is there a high density of road network ? | F41: Assess proportion of roads network and potentilly destabilized soils | G41: Not noticed | H41: =IF(OR(G41=$J$53,G41=$J$54,G41=$J$55),$J$9,$J$8) | I41: =IF(G41=$J$53,$K$53,IF(G41=$J$54,$K$54,$K$55)) -> 1
A42: =A41+1 -> 9 | D42: Communication | E42: is communication reliability an issue during/after extreme weather events ? | F42: Consider reliability of communication networks | G42: Not noticed | H42: =IF(OR(G42=$J$22,G42=$J$23,G42=$J$24),$J$9,$J$8) | I42: =IF(G42=$J$22,$K$22,IF(G42=$J$23,$K$23,$K$24)) -> 1 | J42: List 7 | K42: Clay is bad
J43: Yes | K43: 1
A44: =A43+1 -> 1 | B44: 4 | C44: Potable water | D44: Access | E44: is access to water impacted by changing climate and extreme weather events? | F44: This refers to water for drinking | G44: Not noticed | H44: =IF(OR(G44=$J$53,G44=$J$54,G44=$J$55),$J$9,$J$8) | I44: =IF(G44=$J$53,$K$53,IF(G44=$J$54,$K$54,$K$55)) -> 1 | J44: No | K44: 3
A45: =A44+1 -> 2 | D45: Scarcities | E45: is water supply regularly impacted / interrupted in relation to extreme weather events? | F45: This refers to water for drinking | G45: Not noticed | H45: =IF(OR(G45=$J$53,G45=$J$54,G45=$J$55),$J$9,$J$8) | I45: =IF(G45=$J$53,$K$53,IF(G45=$J$54,$K$54,$K$55)) -> 1 | J45: Not Applicable | K45: 2
A46: =A45+1 -> 3 | D46: Quality | E46: is water quality impacted by changing climate and extreme weather events? | F46: This refers to water for drinking | G46: Not noticed | H46: =IF(OR(G46=$J$53,G46=$J$54,G46=$J$55),$J$9,$J$8) | I46: =IF(G46=$J$53,$K$53,IF(G46=$J$54,$K$54,$K$55)) -> 1
J47: List 8 | K47: Yes is bad
A48: =A47+1 -> 1 | B48: 5 | C48: EBS | D48: Soil | E48: Are there erosion and/or frequent landslides taking place? | F48: This refers to soil instabilities | G48: Not noticed | H48: =IF(OR(G48=$J$22,G48=$J$23,G48=$J$24),$J$9,$J$8) | I48: =IF(G48=$J$22,$K$22,IF(G48=$J$23,$K$23,$K$24)) -> 1 | J48: Yes | K48: 1
A49: =A48+1 -> 2 | D49: LC & P | E49: Are large areas burnt deliberately or from disasters (changes infiltration capacity of soil) | F49: This looks into future risks of reduced infiltration capacities | G49: Not noticed | H49: =IF(OR(G49=$J$53,G49=$J$54,G49=$J$55),$J$9,$J$8) | I49: =IF(G49=$J$53,$K$53,IF(G49=$J$54,$K$54,$K$55)) -> 1 | J49: Unknown | K49: 2
A50: =A49+1 -> 3 | D50: NV | E50: Is there deforestation/land clearing taking place | F50: This looks into future risks of soil destabilisation, loss of vegetative cover, and effects of increasing temperatures | G50: Not noticed | H50: =IF(OR(G50=$J$53,G50=$J$54,G50=$J$55),$J$9,$J$8) | I50: =IF(G50=$J$53,$K$53,IF(G50=$J$54,$K$54,$K$55)) -> 1 | J50: No | K50: 3
A51: =A50+1 -> 4 | D51: Wetland | E51: is the wetland water level often unbalanced (dryer or wetter than usual) | F51: Consider observed imbalance | G51: Not noticed | H51: =IF(OR(G51=$J$22,G51=$J$23,G51=$J$24),$J$9,$J$8) | I51: =IF(G51=$J$22,$K$22,IF(G51=$J$23,$K$23,$K$24)) -> 1
A52: =A51+1 -> 5 | D52: Biodiversity | E52: Is inadequate land use causing loss of biodiversity and/or loss of environmentally protected land? | F52: Consider observations | G52: No | H52: =IF(OR(G52=$J$63,G52=$J$64,G52=$J$65),$J$9,$J$8) | I52: =IF(G52=$J$63,$K$63,IF(G52=$J$64,$K$64,$K$65)) -> 1 | J52: List 9 | K52: Largely is bad
A53: =A52+1 -> 6 | D53: NWB | E53: Do intense rains cause flooding from the nearly water bodies? Do households settle within riperian corridors | F53: Consider changing river courses | G53: Not noticed | H53: =IF(OR(G53=$J$22,G53=$J$23,G53=$J$24),$J$9,$J$8) | I53: =IF(G53=$J$22,$K$22,IF(G53=$J$23,$K$23,$K$24)) -> 1 | J53: Largely | K53: 3
A54: =A53+1 -> 7 | D54: Sea | E54: Are housing and livelihood depending on a stable sea level ? | F54: Consider location of settlement in relation to sea level | G54: Not noticed | H54: =IF(OR(G54=$J$53,G54=$J$54,G54=$J$55),$J$9,$J$8) | I54: =IF(G54=$J$53,$K$53,IF(G54=$J$54,$K$54,$K$55)) -> 1 | J54: Partially | K54: 2
A55: =A54+1 -> 8 | D55: EF | E55: Is environmental contamination from waste and effluents (e.g water bodies) intensifying due to extreme weather events | F55: Consider carrying of wastes due to increasing flood levels | G55: Not noticed | H55: =IF(OR(G55=$J$22,G55=$J$23,G55=$J$24),$J$9,$J$8) | I55: =IF(G55=$J$22,$K$22,IF(G55=$J$23,$K$23,$K$24)) -> 1 | J55: Not noticed | K55: 1
A56: =A55+1 -> 9 | D56: Land use | E56: Is heat increasing and windflow declining within the built up area? | F56: Consider heat and wind flow | G56: Not noticed | H56: =IF(OR(G56=$J$22,G56=$J$23,G56=$J$24),$J$9,$J$8) | I56: =IF(G56=$J$22,$K$22,IF(G56=$J$23,$K$23,$K$24)) -> 1
A57: =A56+1 -> 10 | D57: Topography | E57: Are there low lying settlement areas that flood for a long time because the water cannot drain off, or located within flow paths of storm water | F57: Consider effect of topography in relation to the settlement location | G57: Not noticed | H57: =IF(OR(G57=$J$22,G57=$J$23,G57=$J$24),$J$9,$J$8) | I57: =IF(G57=$J$22,$K$22,IF(G57=$J$23,$K$23,$K$24)) -> 1 | J57: List 9 | K57: Usually is bad
J58: Usually | K58: 3
A59: =A58+1 -> 1 | B59: 6 | C59: Institutions | D59: EWS | E59: Is there a mechansim that provides location based real time information/data to trigger early warning needs? | F59: This inquires about ease of access to real time weather data and related warnings | G59: Not noticed | H59: =IF(OR(G59=$J$53,G59=$J$54,G59=$J$55),$J$9,$J$8) | I59: =IF(G59=$J$53,$K$53,IF(G59=$J$54,$K$54,$K$55)) -> 1 | J59: Sometimes | K59: 2
A60: =A59+1 -> 2 | D60: A & I | E60: Are the county and the community regularly engaging with each other to ensure risk and vulnerability reduction? | F60: This inquires about the interaction between the county and the community | G60: Yes | H60: =IF(OR(G60=$J$63,G60=$J$64,G60=$J$65),$J$9,$J$8) | I60: =IF(G60=$J$48,$K$48,IF(G60=$J$49,$K$49,$K$50)) -> 1 | J60: Never | K60: 1
A61: =A60+1 -> 3 | D61: EC | E61: Is the community aware of the role of the ecosystem in reducing flood hazards though natural infiltration, heat islands through vegetatation cover, destruction through wind blockage, food security etc.... | F61: This inquires about climate risk awareness among the community members | G61: Not noticed | H61: =IF(OR(G61=$J$53,G61=$J$54,G61=$J$55),$J$9,$J$8) | I61: =IF(G61=$J$53,$K$53,IF(G61=$J$54,$K$54,$K$55)) -> 1
A62: =A61+1 -> 4 | D62: R/RP | E62: Are there budgeted ressources effectively directed toward the planned activities to benefit the settlement ? | F62: This inquires about budget execution | G62: Yes | H62: =IF(OR(G62=$J$63,G62=$J$64,G62=$J$65),$J$9,$J$8) | I62: =IF(G62=$J$48,$K$48,IF(G62=$J$49,$K$49,$K$50)) -> 1 | J62: List 10 | K62: Yes is bad
A63: =A62+1 -> 5 | D63: HFO | E63: Are the health services functional and accessible during severe climate and weather evants? | F63: Tis targets functionality of health facilities as critical facilties | G63: Yes | H63: =IF(OR(G63=$J$63,G63=$J$64,G63=$J$65),$J$9,$J$8) | I63: =IF(G63=$J$48,$K$48,IF(G63=$J$49,$K$49,$K$50)) -> 1 | J63: Yes | K63: 3
A64: =A63+1 -> 6 | D64: DP | E64: Can residents access evacuation centers or alternative shelter if needed and have safe evacuation routes been identified ? | G64: Yes | H64: =IF(OR(G64=$J$63,G64=$J$64,G64=$J$65),$J$9,$J$8) | I64: =IF(G64=$J$48,$K$48,IF(G64=$J$49,$K$49,$K$50)) -> 1 | J64: No | K64: 1
A65: =A64+1 -> 7 | D65: DR | E65: Can residents access aid and assistance in case of disaster if needed ? | G65: Yes | H65: =IF(OR(G65=$J$63,G65=$J$64,G65=$J$65),$J$9,$J$8) | I65: =IF(G65=$J$48,$K$48,IF(G65=$J$49,$K$49,$K$50)) -> 1 | J65: Unknown | K65: 2
A66: =A65+1 -> 8 | D66: PFR | E66: Is disbursement for recovery funds clear and effective? | G66: Yes | H66: =IF(OR(G66=$J$63,G66=$J$64,G66=$J$65),$J$9,$J$8) | I66: =IF(G66=$J$48,$K$48,IF(G66=$J$49,$K$49,$K$50)) -> 1
A67: =A66+1 -> 9 | D67: PFM | E67: Is maintenance and repair of public infrastructures budgeted for and the disbursement meachnism is clear? | F67: This is a verificaiton of budgeting at County level | G67: Yes | H67: =IF(OR(G67=$J$63,G67=$J$64,G67=$J$65),$J$9,$J$8) | I67: =IF(G67=$J$48,$K$48,IF(G67=$J$49,$K$49,$K$50)) -> 1

Sheet Adaptive Capacity
F7: NOTE: ONCE YOU CLICK THIS BUTTON YOU CANNOT UNDO YOUR ACTIONS
B8: CURRENT ADAPTIVE CAPACITY | J8: No Selecton Done!
J9: =""
B10: Adaptive Capacity | E10: Question | F10: Comments/Description | G10: Answer? | H10: Add Note On Each Answer | I10: Rating? | J10: List 1 | K10: no is bad
A11: 1 | B11: 1 | C11: Livelihoods | D11: Food Security | E11: Are there adequate areas formally available to practice urban agriculture | F11: Consider provisions in LPLUDP's and Community Development Plans | G11: Yes | H11: =IF(OR(G11=$J$11,G11=$J$12,G11=$J$13),$J$9,$J$8) | I11: =IF(G11=$J$11,$K$11,IF(G11=$J$12,$K$12,$K$13)) -> 3 | J11: No | K11: 1
D12: Grazing/Farm Land | E12: Are there adequate areas formally available for grazing | F12: Consider provisions in LPLUDP's and Community Development Plans | G12: Yes | H12: =IF(OR(G12=$J$11,G12=$J$12,G12=$J$13),$J$9,$J$8) | I12: =IF(G12=$J$11,$K$11,IF(G12=$J$12,$K$12,$K$13)) -> 3 | J12: Sometimes | K12: 2
A13: =A5+1 -> 1 | D13: Crops | E13: Are there mechanims to diversify crops, share unaffected crops and farming locations, and store harvest to protect it? | F13: Consider crop protection from weather events and capacity to diversify crops | G13: Yes | H13: =IF(OR(G13=$J$17,G13=$J$18,G13=$J$19),$J$9,$J$8) | I13: =IF(G13=$J$17,$K$17,IF(G13=$J$18,$K$18,$K$19)) -> 3 | J13: Yes | K13: 3
A14: =A3+1 -> 1 | D14: Livestock | E14: Are there adequate areas identofied and mechanisms to timely rescue and relocate animals to minimise imact from hazards | F14: Consider provisions in LPLUDP's, Community Development Plans and Evacuation Plans | G14: Yes | H14: =IF(OR(G14=$J$17,G14=$J$18,G14=$J$19),$J$9,$J$8) | I14: =IF(G14=$J$17,$K$17,IF(G14=$J$18,$K$18,$K$19)) -> 3
A15: =A4+1 -> 1 | D15: Fishstock | E15: Are there meachnisms that prevent overfishing (monitoring, net size regulations…) and support fishermen with alternatives, such as fish farming | F15: Consider provisions in LPLUDP's and Community Development Plans | G15: Yes | H15: =IF(OR(G15=$J$11,G15=$J$12,G15=$J$13),$J$9,$J$8) | I15: =IF(G15=$J$11,$K$11,IF(G15=$J$12,$K$12,$K$13)) -> 3
A16: =A5+1 -> 1 | D16: Local commerce | E16: Are there diverse economic opportunities in the area? | F16: Consider mixed uses opportunities and access to small business units | G16: Yes | H16: =IF(OR(G16=$J$11,G16=$J$12,G16=$J$13),$J$9,$J$8) | I16: =IF(G16=$J$11,$K$11,IF(G16=$J$12,$K$12,$K$13)) -> 3 | J16: List 2 | K16: no is bad
A17: =A7+1 -> 1 | D17: Gender | E17: Are there mechanisms to ensure privacy, safety and access to reproductve health care for women at all times? | F17: Consider access to health care services and DRM plans | G17: Yes | H17: =IF(OR(G17=$J$11,G17=$J$12,G17=$J$13),$J$9,$J$8) | I17: =IF(G17=$J$11,$K$11,IF(G17=$J$12,$K$12,$K$13)) -> 3 | J17: No | K17: 1
A18: =A8+1 -> 1 | D18: Conviviality | E18: Is there a mechanism to mitigate disputes over diminuished resources before escalation? | F18: Consider activities and capacities of SEC's, GRC's, Environmental and Land Courts (ELC), and public awareness and information | G18: Yes | H18: =IF(OR(G18=$J$11,G18=$J$12,G18=$J$13),$J$9,$J$8) | I18: =IF(G18=$J$11,$K$11,IF(G18=$J$12,$K$12,$K$13)) -> 3 | J18: Yes | K18: 3
A19: =A9+1 -> 1 | D19: Education | E19: Are there mechanisms for children to receive education at all times? | F19: Consider access to education, DRM plans, and provisions to ensure protection of schools from hazards | G19: Yes | H19: =IF(OR(G19=$J$11,G19=$J$12,G19=$J$13),$J$9,$J$8) | I19: =IF(G19=$J$11,$K$11,IF(G19=$J$12,$K$12,$K$13)) -> 3 | J19: Unknown | K19: 2
A20: =A10+1 -> 1 | D20: WFI/WFDU | E20: Are there provisions to harvest and store rain and surface water for irrigation during dry periods? | F20: Consider rain and surface water harvesting and storage available to subsistence farmers | G20: Yes | H20: =IF(OR(G20=$J$11,G20=$J$12,G20=$J$13),$J$9,$J$8) | I20: =IF(G20=$J$11,$K$11,IF(G20=$J$12,$K$12,$K$13)) -> 3
A21: =A11+1 -> 2 | D21: ATF/I | E21: Are most households health insured and insured for cases of disaster ? | F21: Consider rate of health insurance and provisions to help accsess disaster insurance | G21: Yes | H21: =IF(OR(G21=$J$11,G21=$J$12,G21=$J$13),$J$9,$J$8) | I21: =IF(G21=$J$11,$K$11,IF(G21=$J$12,$K$12,$K$13)) -> 3 | J21: List 3 | K21: no is bad
D22: Disaster Events | E22: Is the community aware of the evacuation routes and evacuation centers, and trained for cases of disaster? | F22: Consider availability and awareness of evacuaiotn plans and response mechanisms | G22: Yes | H22: =IF(OR(G22=$J$11,G22=$J$12,G22=$J$13),$J$9,$J$8) | I22: =IF(G22=$J$11,$K$11,IF(G22=$J$12,$K$12,$K$13)) -> 3 | J22: No | K22: 1
J23: Unknown | K23: 2
A24: =A22+1 -> 1 | B24: 2 | C24: Health & Safety | D24: Borne Diseases | E24: Are communities supported to protect and keep healthy during climate related hazards or extreme weather events? | F24: Consider provisions in Community Development Plans, budgets and awareness and information | G24: Yes | H24: =IF(OR(G24=$J$11,G24=$J$12,G24=$J$13),$J$9,$J$8) | I24: =IF(G24=$J$11,$K$11,IF(G24=$J$12,$K$12,$K$13)) -> 3 | J24: Yes | K24: 3
A25: =A21+1 -> 3 | D25: SLUP&C | E25: Is land use planning and enforcement functional and awareness raised about areas at risk? | F25: Consider public awareness of hazardous zones | G25: Yes | H25: =IF(OR(G25=$J$17,G25=$J$18,G25=$J$19),$J$9,$J$8) | I25: =IF(G25=$J$17,$K$17,IF(G25=$J$18,$K$18,$K$19)) -> 3
A26: =A22+1 -> 1 | D26: SWM | E26: Is there effective solid waste management ? | F26: Consider SWM plans and functionality of SWM | G26: Yes | H26: =IF(OR(G26=$J$11,G26=$J$12,G26=$J$13),$J$9,$J$8) | I26: =IF(G26=$J$11,$K$11,IF(G26=$J$12,$K$12,$K$13)) -> 3
A27: =A23+1 -> 1 | D27: LWM | E27: Is there adequate sanitation that is not vulnerable to severe weather events ? | F27: Sanitation solutions respond to the hydrological conditions and are resilient | G27: Yes | H27: =IF(OR(G27=$J$11,G27=$J$12,G27=$J$13),$J$9,$J$8) | I27: =IF(G27=$J$11,$K$11,IF(G27=$J$12,$K$12,$K$13)) -> 3
A28: =A24+1 -> 2 | D28: ATHS | E28: Is there a mechanism that maintains or immediately recovers access to health services when adversely affected ? | F28: Consider DRM plans, evacuaiton plans, and disaster response times and recovery budgets | G28: Yes | H28: =IF(OR(G28=$J$17,G28=$J$18,G28=$J$19),$J$9,$J$8) | I28: =IF(G28=$J$17,$K$17,IF(G28=$J$18,$K$18,$K$19)) -> 3
A29: =A28+1 -> 3 | D29: ATHE | E29: Is the county holding industrial polluters accountable ? | F29: Consider enforcement of environmental regulatioons | G29: Yes | H29: =IF(OR(G29=$J$11,G29=$J$12,G29=$J$13),$J$9,$J$8) | I29: =IF(G29=$J$11,$K$11,IF(G29=$J$12,$K$12,$K$13)) -> 3
A31: =A29+1 -> 4 | B31: 3 | C31: Assets and Utilities | D31: Housing | E31: Is there access to a reinstatement program or mechanism for damaged or lost shelter for affected community members ? | F31: Consider access to finance for home recovery after disaster | G31: Yes | H31: =IF(OR(G31=$J$22,G31=$J$23,G31=$J$24),$J$9,$J$8) | I31: =IF(G31=$J$22,$K$22,IF(G31=$J$23,$K$23,$K$24)) -> 3
A32: =A22+1 -> 1 | D32: Public facilities | E32: Is here a mechanism that maintains or immediately recovers access to critical public services when adversely affected ? | F32: Consider immediate recovery of critical infrastucture | G32: Yes | H32: =IF(OR(G32=$J$17,G32=$J$18,G32=$J$19),$J$9,$J$8) | I32: =IF(G32=$J$17,$K$17,IF(G32=$J$18,$K$18,$K$19)) -> 3
A33: =A32+1 -> 2 | D33: SWD | E33: Are storm water flows fully planned and managed from source up to outlet/for the whole watershed/including use of natural infiltration? | F33: Consider storm water management planning based on location based hydrological assessment | G33: Yes | H33: =IF(OR(G33=$J$17,G33=$J$18,G33=$J$19),$J$9,$J$8) | I33: =IF(G33=$J$17,$K$17,IF(G33=$J$18,$K$18,$K$19)) -> 3
A34: =A33+1 -> 3 | D34: Sanitary facilities | E34: Are sanitary facilities adequate and properly designed in respect of ground water protection? | F34: This is specific to household sanitation; consider techncial assistance to ensure adequacy | G34: Yes | H34: =IF(OR(G34=$J$17,G34=$J$18,G34=$J$19),$J$9,$J$8) | I34: =IF(G34=$J$17,$K$17,IF(G34=$J$18,$K$18,$K$19)) -> 3
A35: =A25+1 -> 4 | D35: Sewer lines | E35: Are sewers properly designed in respect of ground water protection and fit for the local situaiton (and capability to connect)? | F35: Consider adequate infrastucture planning based on location based hydrological assessment | G35: Yes | H35: =IF(OR(G35=$J$17,G35=$J$18,G35=$J$19),$J$9,$J$8) | I35: =IF(G35=$J$17,$K$17,IF(G35=$J$18,$K$18,$K$19)) -> 3
A36: =A28+1 -> 3 | D36: Power lines/supply | E36: Are there means to continously maintain the functionality of the most critical services and to provide access to energy, such as hospitals? | F36: Consider immediate recovery of critical infrastucture | G36: Yes | H36: =IF(OR(G36=$J$17,G36=$J$18,G36=$J$19),$J$9,$J$8) | I36: =IF(G36=$J$17,$K$17,IF(G36=$J$18,$K$18,$K$19)) -> 3
A37: =A36+1 -> 4 | D37: Energy for HH use | E37: Are there programs that facilitate access to alternative, green and renewable sources of energy for lighting and cooking ? | F37: Consider grid and solar kits | G37: Yes | H37: =IF(OR(G37=$J$17,G37=$J$18,G37=$J$19),$J$9,$J$8) | I37: =IF(G37=$J$17,$K$17,IF(G37=$J$18,$K$18,$K$19)) -> 3
A38: =A37+1 -> 5 | D38: Water pipes | E38: Are water pipes properly planned and the layout and access points fit for the local situation? | F38: Consider adequate infrastucture planning based on location based hydrological assessment | G38: Yes | H38: =IF(OR(G38=$J$17,G38=$J$18,G38=$J$19),$J$9,$J$8) | I38: =IF(G38=$J$17,$K$17,IF(G38=$J$18,$K$18,$K$19)) -> 3
A39: =A38+1 -> 6 | D39: PWT | E39: Is the relevant water treatment facility protected from hazards by the provider? | F39: Consider infrastructure protection measures | G39: Yes | H39: =IF(OR(G39=$J$17,G39=$J$18,G39=$J$19),$J$9,$J$8) | I39: =IF(G39=$J$17,$K$17,IF(G39=$J$18,$K$18,$K$19)) -> 3
A40: =A39+1 -> 7 | D40: Water Storage | E40: Is water storage available, protected from hazards ? | F40: Consider availability of water storage and its protetcton | G40: Yes | H40: =IF(OR(G40=$J$17,G40=$J$18,G40=$J$19),$J$9,$J$8) | I40: =IF(G40=$J$17,$K$17,IF(G40=$J$18,$K$18,$K$19)) -> 3
A41: =A40+1 -> 8 | D41: R & T | E41: Is the settlement accessible in all weather conditions (access to/and within)? | F41: Consider adequate infrastucture planning based on location based hydrological assessment | G41: Yes | H41: =IF(OR(G41=$J$22,G41=$J$23,G41=$J$24),$J$9,$J$8) | I41: =IF(G41=$J$22,$K$22,IF(G41=$J$23,$K$23,$K$24)) -> 3
A42: =A41+1 -> 9 | D42: Communication | E42: Is access to communication ensured in all weather conditions ? | F42: Consider adequate infrastucture planning based on location based hydrological assessment | G42: Yes | H42: =IF(OR(G42=$J$22,G42=$J$23,G42=$J$24),$J$9,$J$8) | I42: =IF(G42=$J$22,$K$22,IF(G42=$J$23,$K$23,$K$24)) -> 3
A44: =A43+1 -> 1 | B44: 4 | C44: Potable water | D44: Access | E44: Are there provisions to ensure access to water in the case of emergencies/scarcities? | F44: This includes prepositioning of water for drinking | G44: Yes | H44: =IF(OR(G44=$J$22,G44=$J$23,G44=$J$24),$J$9,$J$8) | I44: =IF(G44=$J$22,$K$22,IF(G44=$J$23,$K$23,$K$24)) -> 3
A45: =A44+1 -> 2 | D45: Scarcities | E45: Are there provisions to ensure sufficient quantities of water in dry seasons / during interruted water supply ? | F45: This includes prepositioning of water for drinking | G45: Yes | H45: =IF(OR(G45=$J$11,G45=$J$12,G45=$J$13),$J$9,$J$8) | I45: =IF(G45=$J$11,$K$11,IF(G45=$J$12,$K$12,$K$13)) -> 3
A46: =A45+1 -> 3 | D46: Quality | E46: Are there provisions to ensure drinking water quality ? | F46: This includes prepositioning of water for drinking | G46: Yes | H46: =IF(OR(G46=$J$22,G46=$J$23,G46=$J$24),$J$9,$J$8) | I46: =IF(G46=$J$22,$K$22,IF(G46=$J$23,$K$23,$K$24)) -> 3
A48: =A47+1 -> 1 | B48: 5 | C48: EBS | D48: Soil | E48: Are geological assessments provenly considered in land use planning and engineeing designs? | F48: Consider adequate planning and design based on location based assessment | G48: Yes | H48: =IF(OR(G48=$J$22,G48=$J$23,G48=$J$24),$J$9,$J$8) | I48: =IF(G48=$J$22,$K$22,IF(G48=$J$23,$K$23,$K$24)) -> 3
A49: =A48+1 -> 2 | D49: LC & P | E49: Is sufficient permeability considered in the settlement plans as part of storm water management and infiltration ? | F49: Consider areas that allow for infiltration | G49: Yes | H49: =IF(OR(G49=$J$22,G49=$J$23,G49=$J$24),$J$9,$J$8) | I49: =IF(G49=$J$22,$K$22,IF(G49=$J$23,$K$23,$K$24)) -> 3
A50: =A49+1 -> 3 | D50: NV | E50: Is sufficient vegetation considered in the settlement plans as part of mitigation of extreme heat? | F50: Consider vegetative cover | G50: Yes | H50: =IF(OR(G50=$J$22,G50=$J$23,G50=$J$24),$J$9,$J$8) | I50: =IF(G50=$J$22,$K$22,IF(G50=$J$23,$K$23,$K$24)) -> 3
A51: =A50+1 -> 4 | D51: Wetland | E51: Are wetlands considred as part of the settlement plans and enforcement to maintain their natural functionality? | F51: Consider respect to wetland areas | G51: Yes | H51: =IF(OR(G51=$J$22,G51=$J$23,G51=$J$24),$J$9,$J$8) | I51: =IF(G51=$J$22,$K$22,IF(G51=$J$23,$K$23,$K$24)) -> 3
A52: =A51+1 -> 5 | D52: Biodiversity | E52: Are areas for undisturbed habitat/nisting/ and migrational routes respected as part of the settlement plans for conservation purposes and to mitigate human wildlife conflict ? | F52: Consider respect to natural habitat | G52: Yes | H52: =IF(OR(G52=$J$22,G52=$J$23,G52=$J$24),$J$9,$J$8) | I52: =IF(G52=$J$22,$K$22,IF(G52=$J$23,$K$23,$K$24)) -> 3
A53: =A52+1 -> 6 | D53: NWB | E53: Is the river bed and flood plain of the nearby water body respected and/or springs protected from pollution? | F53: Consider respect to natural water flows | G53: Yes | H53: =IF(OR(G53=$J$22,G53=$J$23,G53=$J$24),$J$9,$J$8) | I53: =IF(G53=$J$22,$K$22,IF(G53=$J$23,$K$23,$K$24)) -> 3
A54: =A53+1 -> 7 | D54: Sea | E54: Is the sea and tidal movements respected in the settlement plans ? | F54: Consider respect to tidal flows | G54: Yes | H54: =IF(OR(G54=$J$22,G54=$J$23,G54=$J$24),$J$9,$J$8) | I54: =IF(G54=$J$22,$K$22,IF(G54=$J$23,$K$23,$K$24)) -> 3
A55: =A54+1 -> 8 | D55: EF | E55: Are there environmnetal awareness programs conducted, and industrial polluters held responsible? | F55: Consider awareness for environmental regulations | G55: Yes | H55: =IF(OR(G55=$J$22,G55=$J$23,G55=$J$24),$J$9,$J$8) | I55: =IF(G55=$J$22,$K$22,IF(G55=$J$23,$K$23,$K$24)) -> 3
A56: =A55+1 -> 9 | D56: Land use | E56: Are land use planning and enforcement by the local government effective and discourage settlement on inadequate land / in risky areas, and is the public aware of the importance in disaster risk reduction? | F56: Consider respect to hazardous areas and awareness | G56: Yes | H56: =IF(OR(G56=$J$22,G56=$J$23,G56=$J$24),$J$9,$J$8) | I56: =IF(G56=$J$22,$K$22,IF(G56=$J$23,$K$23,$K$24)) -> 3
A57: =A56+1 -> 10 | D57: Topography | E57: Are there vegetative soil stabilisation measures combined with adaptive road network planning and storm water management planning? | F57: Consider erosion control measures | G57: Yes | H57: =IF(OR(G57=$J$22,G57=$J$23,G57=$J$24),$J$9,$J$8) | I57: =IF(G57=$J$22,$K$22,IF(G57=$J$23,$K$23,$K$24)) -> 3
A59: =A58+1 -> 1 | B59: 6 | C59: Institutions | D59: EWS | E59: Is there an Early Warning System with SOP's, responsibilities assigned and the community trained to respond in cases if emergency? | F59: Consider existence of plan and awareness of its content | G59: Yes | H59: =IF(OR(G59=$J$22,G59=$J$23,G59=$J$24),$J$9,$J$8) | I59: =IF(G59=$J$22,$K$22,IF(G59=$J$23,$K$23,$K$24)) -> 3
A60: =A59+1 -> 2 | D60: A & I | E60: Is access to climate related information and understanding facilitated, such as warnings of weather events? | F60: Consider climate change awareness | G60: Yes | H60: =IF(OR(G60=$J$22,G60=$J$23,G60=$J$24),$J$9,$J$8) | I60: =IF(G60=$J$22,$K$22,IF(G60=$J$23,$K$23,$K$24)) -> 3
A61: =A60+1 -> 3 | D61: EC | E61: Does the local government effectively communicate to the community during disasters (is there a mechanism)? | F61: Consider evacuatio plans and disaster response mechanims | G61: Yes | H61: =IF(OR(G61=$J$22,G61=$J$23,G61=$J$24),$J$9,$J$8) | I61: =IF(G61=$J$22,$K$22,IF(G61=$J$23,$K$23,$K$24)) -> 3
A62: =A61+1 -> 4 | D62: R/RP | E62: Is there an established ressource planning and budgeting process at county level which is transparent to the community ? | F62: Consider participatory CIDP pocess and budgeting | G62: Yes | H62: =IF(OR(G62=$J$22,G62=$J$23,G62=$J$24),$J$9,$J$8) | I62: =IF(G62=$J$22,$K$22,IF(G62=$J$23,$K$23,$K$24)) -> 3
A63: =A62+1 -> 5 | D63: HFO | E63: Is there a mechanism to ensure accessibility and functionaility of health services at all times (including access to water, electricity, food and personnell)? | F63: Consider maintained access to water, electricity, personnel and supplies | G63: Yes | H63: =IF(OR(G63=$J$22,G63=$J$23,G63=$J$24),$J$9,$J$8) | I63: =IF(G63=$J$22,$K$22,IF(G63=$J$23,$K$23,$K$24)) -> 3
A64: =A63+1 -> 6 | D64: DP | E64: Are there DRM plans, evacuation plans and evaculation centers for cases of disaster, and the neccessary supplies predispositioned? | F64: Consider availability and awareness | G64: Yes | H64: =IF(OR(G64=$J$22,G64=$J$23,G64=$J$24),$J$9,$J$8) | I64: =IF(G64=$J$22,$K$22,IF(G64=$J$23,$K$23,$K$24)) -> 3
A65: =A64+1 -> 7 | D65: DR | E65: Is there a mechanism to quickly mobilise disaster response staff and budget in case of emergency? | F65: Consider responsibilities and equipment | G65: Yes | H65: =IF(OR(G65=$J$22,G65=$J$23,G65=$J$24),$J$9,$J$8) | I65: =IF(G65=$J$22,$K$22,IF(G65=$J$23,$K$23,$K$24)) -> 3
A66: =A65+1 -> 8 | D66: PFR | E66: Does the local government have the capacity and finance to quickly respond to disasters and access resources for disaster recovery in case of emergency? | F66: Consider access to funds in emergency situations | G66: Yes | H66: =IF(OR(G66=$J$22,G66=$J$23,G66=$J$24),$J$9,$J$8) | I66: =IF(G66=$J$22,$K$22,IF(G66=$J$23,$K$23,$K$24)) -> 3
A67: =A66+1 -> 9 | D67: PFM | E67: Does the local government have the capacity and finance to manage and maintain / reinstate damaged infrastructure, and is infrastructue maintenance institutionalised? | F67: Consider access to funds for repairs | G67: Yes | H67: =IF(OR(G67=$J$22,G67=$J$23,G67=$J$24),$J$9,$J$8) | I67: =IF(G67=$J$22,$K$22,IF(G67=$J$23,$K$23,$K$24)) -> 3

Sheet RVAT_Output
C5: To view a synthesis of all the responses, click on the tabs below:
C10: To view the output of the risk and vulnerability assessment, click on the tabs below:
X27: +
B30: HAZARD
B32: CURRENT
B33: The table below illustrates the current climate hazards | AE33: The graph below illustrates the current climate hazards
C36: =C190 -> Temperature | D36: =D190 -> App or Freq | I36: =L190 -> Intensity | S36: =U190 -> Impact
C37: =C191 -> Intense Precipitation | D37: =D191 -> App or Freq | I37: =L191 -> Intensity | S37: =U191 -> Impact
C38: =C192 -> Droughts | D38: =D192 -> App or Freq | G38: =I192 -> Timing | N38: =Q192 -> Intensity | U38: =X192 -> Impact
C39: =C193 -> Flooding | D39: =D193 -> App or Freq | G39: =G193 -> Timing | L39: =M193 -> Intensity | Q39: =S193 -> Extent | X39: =X193 -> Impact
C40: =C194 -> Flash Floods | D40: =D194 -> App or Freq | G40: =G194 -> Timing | L40: =M194 -> Intensity | Q40: =S194 -> Extent | X40: =X194 -> Impact
C41: =C195 -> Storms & Upper Winds | D41: =D195 -> App or Freq | I41: =L195 -> Intensity | S41: =U195 -> Impact
C42: =C196 -> Pollution | D42: =D196 -> App or Freq | I42: =L196 -> Intensity | S42: =U196 -> Impact
C43: =C197 -> LUI | D43: =D197 -> Applicability | I43: =L197 -> Impact | S43: =U197 -> Sensitization
C44: =C208 -> Other Factors | D44: =D198 -> Fire/wildfires | F44: =G198 -> Lightning | H44: =K198 -> Snow | K44: =N198 -> Hail | M44: =Q198 -> EA or VA | Q44: =X198 -> Soil Extraction | V44: =Y198 -> Deforestation | Y44: =Z198 -> Ubarnization
H46: Legend: | K46: Low | N46: Medium | R46: High
B50: EXPOSURE
B52: CURRENT | AD52: The graph below illustrates the current levels of exposure
B53: The table below illustrates the current levels of exposure
C55: =B210 -> Livelihoods | D55: =C210 -> Food Security | E55: =D210 -> Grazing/Farm Land | G55: =F210 -> Crops | I55: =H210 -> Livestock | L55: =K210 -> Fishstock | O55: =N210 -> Local commerce | S55: =R210 -> Gender | W55: =U210 -> Conviviality | Y55: =X210 -> Education | Z55: =Y210 -> WFI/WFDU | AA55: =Z210 -> ATF/I | AB55: =AA210 -> Disaster Events
C56: =B211 -> Health & Safety | D56: =C211 -> Borne Diseases | G56: =D211 -> SLUP&C | L56: =G211 -> SWM | S56: =L211 -> LWM | Y56: =R211 -> ATHS | AA56: =Y211 -> ATHE
C57: =B212 -> Assets and Utilities | D57: =C212 -> Housing | E57: =D212 -> Public facilities | G57: =F212 -> SWD | I57: =H212 -> Sanitary facilities | L57: =K212 -> Sewer lines | O57: =N212 -> Power lines/supply | S57: =R212 -> Energy for HH use | W57: =U212 -> Water pipes | Y57: =X212 -> PWT | Z57: =Y212 -> Water Storage | AA57: =Z212 -> R & T | AB57: =AA212 -> Communication
C58: =B213 -> Potable water | D58: =C213 -> Access | K58: =J213 -> Scarcities | Y58: =X213 -> Quality
C59: =B214 -> EBS | D59: =C214 -> Soil | F59: =D214 -> LC & P | I59: =G214 -> NV | M59: =J214 -> Wetland | R59: =M214 -> Biodiversity | W59: =R214 -> NWB | Y59: =X214 -> Sea | Z59: =Y214 -> EF | AA59: =Z214 -> Land use | AB59: =AA214 -> Topography
C60: =B215 -> Institutions | D60: =C215 -> EWS | F60: =D215 -> A & I | I60: =G215 -> EC | L60: =K215 -> R/RP | P60: =O215 -> HFO | X60: =V215 -> DP | Z60: =Y215 -> DR | AA60: =Z215 -> PFR | AB60: =AA215 -> PFM
H63: Legend: | K63: Low | N63: Medium | R63: High
B66: SENSITIVITY
B68: CURRENT | AD68: The graph below illustrates the current levels of sensitivity
B69: The table below illustrates the current levels of sensitivity
C71: =B225 -> Livelihoods | D71: =C225 -> Food Security | E71: =D225 -> Grazing/Farm Land | G71: =F225 -> Crops | I71: =H225 -> Livestock | L71: =K225 -> Fishstock | O71: =N225 -> Local commerce | S71: =R225 -> Gender | W71: =U225 -> Conviviality | Y71: =X225 -> Education | Z71: =Y225 -> WFI/WFDU | AA71: =Z225 -> ATF/I | AB71: =AA225 -> Disaster Events
C72: =B226 -> Health & Safety | D72: =C226 -> Borne Diseases | G72: =D226 -> SLUP&C | L72: =G226 -> SWM | S72: =L226 -> LWM | Y72: =R226 -> ATHS | AA72: =Y226 -> ATHE
C73: =B227 -> Assets and Utilities | D73: =C227 -> Housing | E73: =D227 -> Public facilities | G73: =F227 -> SWD | I73: =H227 -> Sanitary facilities | L73: =K227 -> Sewer lines | O73: =N227 -> Power lines/supply | S73: =R227 -> Energy for HH use | W73: =U227 -> Water pipes | Y73: =X227 -> PWT | Z73: =Y227 -> Water Storage | AA73: =Z227 -> R & T | AB73: =AA227 -> Communication
C74: =B228 -> Potable water | D74: =C228 -> Access | K74: =J228 -> Scarcities | Y74: =X228 -> Quality
C75: =B229 -> EBS | D75: =C229 -> Soil | F75: =D229 -> LC & P | I75: =G229 -> NV | M75: =J229 -> Wetland | R75: =M229 -> Biodiversity | W75: =R229 -> NWB | Y75: =X229 -> Sea | Z75: =Y229 -> EF | AA75: =Z229 -> Land use | AB75: =AA229 -> Topography
C76: =B230 -> Institutions | D76: =C230 -> EWS | F76: =D230 -> A & I | I76: =G230 -> EC | L76: =K230 -> R/RP | P76: =O230 -> HFO | X76: =V230 -> DP | Z76: =Y230 -> DR | AA76: =Z230 -> PFR | AB76: =AA230 -> PFM
H79: Legend: | K79: Low | N79: Medium | R79: High
B82: ADAPTIVE CAPACITY
B84: CURRENT | AF84: The graph below illustrates the current adaptive capacity
B85: The table below illustrates the current adaptive capacity
C87: =B240 -> Livelihoods | D87: =C240 -> Food Security | E87: =D240 -> Grazing/Farm Land | G87: =F240 -> Crops | I87: =H240 -> Livestock | L87: =K240 -> Fishstock | O87: =N240 -> Local commerce | S87: =R240 -> Gender | W87: =U240 -> Conviviality | Y87: =X240 -> Education | Z87: =Y240 -> WFI/WFDU | AA87: =Z240 -> ATF/I | AB87: =AA240 -> Disaster Events
C88: =B241 -> Health & Safety | D88: =C241 -> Borne Diseases | G88: =D241 -> SLUP&C | L88: =G241 -> SWM | S88: =L241 -> LWM | Y88: =R241 -> ATHS | AA88: =Y241 -> ATHE
C89: =B242 -> Assets and Utilities | D89: =C242 -> Housing | E89: =D242 -> Public facilities | G89: =F242 -> SWD | I89: =H242 -> Sanitary facilities | L89: =K242 -> Sewer lines | O89: =N242 -> Power lines/supply | S89: =R242 -> Energy for HH use | W89: =U242 -> Water pipes | Y89: =X242 -> PWT | Z89: =Y242 -> Water Storage | AA89: =Z242 -> R & T | AB89: =AA242 -> Communication
C90: =B243 -> Potable water | D90: =C243 -> Access | K90: =J243 -> Scarcities | Y90: =X243 -> Quality
C91: =B244 -> EBS | D91: =C244 -> Soil | F91: =D244 -> LC & P | I91: =G244 -> NV | M91: =J244 -> Wetland | R91: =M244 -> Biodiversity | W91: =R244 -> NWB | Y91: =X244 -> Sea | Z91: =Y244 -> EF | AA91: =Z244 -> Land use | AB91: =AA244 -> Topography
C92: =B245 -> Institutions | D92: =C245 -> EWS | F92: =D245 -> A & I | I92: =G245 -> EC | L92: =K245 -> R/RP | P92: =O245 -> HFO | X92: =V245 -> DP | Z92: =Y245 -> DR | AA92: =Z245 -> PFR | AB92: =AA245 -> PFM
H95: Legend: | K95: Good | N95: Ave | R95: Poor
B99: VULNERABILITY
B102: CURRENT
B103: The table below illustrates the current vulnerability - viewed by the same categories as 'sensitivity' | AD103: The graph below illustrates the current levels of vulnerability
B104: and 'adaptive capacity'
D106: =B255 -> Livelihoods | F106: =D255 -> Health & Safety | I106: =H255 -> Assets and Utilities | M106: =N255 -> Potable water | P106: =U255 -> EBS | T106: =Y255 -> Institutions
B108: The table below illustrates the current vulnerability - viewed by the same categories as 'exposure'
D110: =B260 -> Livelihoods | F110: =D260 -> Health & Safety | I110: =H260 -> Assets and Utilities | M110: =N260 -> Potable water | P110: =U260 -> EBS | T110: =Y260 -> Institutions
H112: Legend: | K112: Low | N112: Medium | R112: High
C114: The table below illustrates the current levels of vulnerability in more detail | AE114: The graph below illustrates the current levels of vulnerability
C116: =B265 -> Livelihoods | D116: =C265 -> Food Security | E116: =D265 -> Grazing/Farm Land | G116: =F265 -> Crops | I116: =H265 -> Livestock | L116: =K265 -> Fishstock | O116: =N265 -> Local commerce | S116: =R265 -> Gender | W116: =U265 -> Conviviality | Y116: =X265 -> Education | Z116: =Y265 -> WFI/WFDU | AA116: =Z265 -> ATF/I | AB116: =AA265 -> Disaster Events
C117: =B266 -> Health & Safety | D117: =C266 -> Borne Diseases | G117: =D266 -> SLUP&C | L117: =G266 -> SWM | S117: =L266 -> LWM | Y117: =R266 -> ATHS | AA117: =Y266 -> ATHE
C118: =B267 -> Assets and Utilities | D118: =C267 -> Housing | E118: =D267 -> Public facilities | G118: =F267 -> SWD | I118: =H267 -> Sanitary facilities | L118: =K267 -> Sewer lines | O118: =N267 -> Power lines/supply | S118: =R267 -> Energy for HH use | W118: =U267 -> Water pipes | Y118: =X267 -> PWT | Z118: =Y267 -> Water Storage | AA118: =Z267 -> R & T | AB118: =AA267 -> Communication
C119: =B268 -> Potable water | D119: =C268 -> Access | K119: =J268 -> Scarcities | Y119: =X268 -> Quality
C120: =B269 -> EBS | D120: =C269 -> Soil | F120: =D269 -> LC & P | I120: =G269 -> NV | M120: =J269 -> Wetland | R120: =M269 -> Biodiversity | W120: =R269 -> NWB | Y120: =X269 -> Sea | Z120: =Y269 -> EF | AA120: =Z269 -> Land use | AB120: =AA269 -> Topography
C121: =B270 -> Institutions | D121: =C270 -> EWS | F121: =D270 -> A & I | I121: =G270 -> EC | L121: =K270 -> R/RP | P121: =O270 -> HFO | X121: =V270 -> DP | Z121: =Y270 -> DR | AA121: =Z270 -> PFR | AB121: =AA270 -> PFM
H124: Legend: | K124: Low | N124: Medium | R124: High
B128: RISK
B131: CURRENT
B132: The table below illustrates the current levels of risk, by category | AF132: The figure below illustrates the current levels of risk, by category
D134: =B280 -> Livelihoods | F134: =D280 -> Health & Safety | I134: =H280 -> Assets and Utilities | M134: =N280 -> Potable water | P134: =U280 -> EBS | T134: =Y280 -> Institutions
H136: Legend: | K136: Low | N136: Medium | R136: High
B145: The table below illustrates the current levels of risk | AF145: The figure below illustrates the current levels of risk
C147: =B285 -> Livelihoods | D147: =C285 -> Food Security | E147: =D285 -> Grazing/Farm Land | G147: =F285 -> Crops | I147: =H285 -> Livestock | L147: =K285 -> Fishstock | O147: =N285 -> Local commerce | S147: =R285 -> Gender | W147: =U285 -> Conviviality | Y147: =X285 -> Education | Z147: =Y285 -> WFI/WFDU | AA147: =Z285 -> ATF/I | AB147: =AA285 -> Disaster Events
C148: =B286 -> Health & Safety | D148: =C286 -> Borne Diseases | G148: =D286 -> SLUP&C | L148: =G286 -> SWM | S148: =L286 -> LWM | Y148: =R286 -> ATHS | AA148: =Y286 -> ATHE
C149: =B287 -> Assets and Utilities | D149: =C287 -> Housing | E149: =D287 -> Public facilities | G149: =F287 -> SWD | I149: =H287 -> Sanitary facilities | L149: =K287 -> Sewer lines | O149: =N287 -> Power lines/supply | S149: =R287 -> Energy for HH use | W149: =U287 -> Water pipes | Y149: =X287 -> PWT | Z149: =Y287 -> Water Storage | AA149: =Z287 -> R & T | AB149: =AA287 -> Communication
C150: =B288 -> Potable water | D150: =C288 -> Access | K150: =J288 -> Scarcities | Y150: =X288 -> Quality
C151: =B289 -> EBS | D151: =C289 -> Soil | F151: =D289 -> LC & P | I151: =G289 -> NV | M151: =J289 -> Wetland | R151: =M289 -> Biodiversity | W151: =R289 -> NWB | Y151: =X289 -> Sea | Z151: =Y289 -> EF | AA151: =Z289 -> Land use | AB151: =AA289 -> Topography
C152: =B290 -> Institutions | D152: =C290 -> EWS | F152: =D290 -> A & I | I152: =G290 -> EC | L152: =K290 -> R/RP | P152: =O290 -> HFO | X152: =V290 -> DP | Z152: =Y290 -> DR | AA152: =Z290 -> PFR | AB152: =AA290 -> PFM
H155: Legend: | K155: Low | N155: Medium | R155: High
B189: HAZARDS - CURRENT
C190: =$X$338 -> Temperature | D190: =Y338 -> App or Freq | L190: =Y339 -> Intensity | U190: =Y340 -> Impact | AB190: Current Hazard | AD190: =Z337 -> Rating? | AF190: =AC337 -> Exposure | AJ190: =AI337 -> Sensitivity | AN190: =AO337 -> Adaptive Capacity | AR190: Vulnurability 1 | AW190: Current Risk
C191: =$X$342 -> Intense Precipitation | D191: =Y342 -> App or Freq | L191: =Y343 -> Intensity | U191: =Y344 -> Impact | AB191: 1 | AC191: =X338 -> Temperature | AD191: =Y338 -> App or Freq | AE191: =AB338 -> High | AF191: =AC338 -> 1 | AG191: =AD338 -> Livelihoods | AH191: =AE338 -> Food Security | AI191: =AH338 -> Low | AJ191: =AI338 -> 1 | AK191: =AJ338 -> Livelihoods | AL191: =AK338 -> Food Security | AM191: =AN338 -> Low | AN191: =AO338 -> 1 | AO191: =AP338 -> Livelihoods | AP191: =AQ338 -> Food Security | AQ191: =AT338 -> Good | AR191: =$AK$191 -> Livelihoods | AS191: =BJ338 -> Low | AW191: =AR198 -> Livelihoods | AX191: =BJ354 -> Low
C192: =$X$346 -> Droughts | D192: =Y346 -> App or Freq | I192: =Y347 -> Timing | Q192: =Y348 -> Intensity | X192: =Y349 -> Impact | AD192: =Y339 -> Intensity | AE192: =AB339 -> Low | AH192: =AE339 -> Grazing/Farm Land | AI192: =AH339 -> Low | AL192: =AK339 -> Grazing/Farm Land | AM192: =AN339 -> Low | AP192: =AQ339 -> Grazing/Farm Land | AQ192: =AT339 -> Good | AR192: =$AK$204 -> Health & Safety | AS192: =BJ339 -> Low | AW192: =AR199 -> Health & Safety | AX192: =BJ355 -> Low
C193: =$X$351 -> Flooding | D193: =Y351 -> App or Freq | G193: =Y352 -> Timing | M193: =Y353 -> Intensity | S193: =Y354 -> Extent | X193: =Y355 -> Impact | AD193: =Y340 -> Impact | AE193: =AB340 -> Low | AH193: =AE340 -> Crops | AI193: =AH340 -> Low | AL193: =AK340 -> Crops | AM193: =AN340 -> Low | AP193: =AQ340 -> Crops | AQ193: =AT340 -> Good | AR193: =$AK$211 -> Assets and Utilities | AS193: =BJ340 -> Low | AW193: =AR200 -> Assets and Utilities | AX193: =BJ356 -> Low
C194: =$X$357 -> Flash Floods | D194: =Y357 -> App or Freq | G194: =Y358 -> Timing | M194: =Y359 -> Intensity | S194: =Y360 -> Extent | X194: =Y361 -> Impact | AB194: =" " | AD194: =Y341 | AH194: =AE341 -> Livestock | AI194: =AH341 -> Low | AL194: =AK341 -> Livestock | AM194: =AN341 -> Low | AP194: =AQ341 -> Livestock | AQ194: =AT341 -> Good | AR194: =$AK$224 -> Potable water | AS194: =BJ341 -> Low | AW194: =AR201 -> Potable water | AX194: =BJ357 -> Low
C195: =$X$363 -> Storms & Upper Winds | D195: =Y363 -> App or Freq | L195: =Y364 -> Intensity | U195: =Y365 -> Impact | AB195: 2 | AC195: =X342 -> Intense Precipitation | AD195: =Y342 -> App or Freq | AE195: =AB342 -> Low | AH195: =AE342 -> Fishstock | AI195: =AH342 -> Low | AL195: =AK342 -> Fishstock | AM195: =AN342 -> Low | AP195: =AQ342 -> Fishstock | AQ195: =AT342 -> Good | AR195: =$AK$228 -> EBS | AS195: =BJ342 -> Low | AW195: =AR202 -> EBS | AX195: =BJ358 -> Low
C196: =$X$367 -> Pollution | D196: =Y367 -> App or Freq | L196: =Y368 -> Intensity | U196: =Y369 -> Impact | AD196: =Y343 -> Intensity | AE196: =AB343 -> Low | AH196: =AE343 -> Local commerce | AI196: =AH343 -> Low | AL196: =AK343 -> Local commerce | AM196: =AN343 -> Low | AP196: =AQ343 -> Local commerce | AQ196: =AT343 -> Good | AR196: =$AK$239 -> Institutions | AS196: =BJ343 -> Low | AW196: =AR203 -> Institutions | AX196: =BJ359 -> Low
C197: =$X$371 -> LUI | D197: =Y371 -> Applicability | L197: =Y372 -> Impact | U197: =Y373 -> Sensitization | AD197: =Y344 -> Impact | AE197: =AB344 -> Low | AH197: =AE344 -> Gender | AI197: =AH344 -> Low | AL197: =AK344 -> Gender | AM197: =AN344 -> Low | AP197: =AQ344 -> Gender | AQ197: =AT344 -> Good
C198: =$X$375 -> Other Factors | D198: =Y375 -> Fire/wildfires | G198: =Y376 -> Lightning | K198: =Y377 -> Snow | N198: =Y378 -> Hail | Q198: =Y379 -> EA or VA | X198: =Y380 -> Soil Extraction | Y198: =Y381 -> Deforestation | Z198: =Y382 -> Ubarnization | AB198: =" " | AC198: =X345 | AD198: =Y345 | AH198: =AE345 -> Conviviality | AI198: =AH345 -> Low | AL198: =AK345 -> Conviviality | AM198: =AN345 -> Low | AP198: =AQ345 -> Conviviality | AQ198: =AT345 -> Good | AR198: =$AV$338 -> Livelihoods | AS198: =BJ338 -> Low
B199: CURRENT | AB199: 3 | AC199: =X346 -> Droughts | AD199: =Y346 -> App or Freq | AE199: =AB346 -> Low | AH199: =AE346 -> Education | AI199: =AH346 -> Low | AL199: =AK346 -> Education | AM199: =AN346 -> Low | AP199: =AQ346 -> Education | AQ199: =AT346 -> Good | AR199: =$AV$351 -> Health & Safety | AS199: =BJ339 -> Low
C200: =$X$338 -> Temperature | D200: =AE191 -> High | L200: =AE192 -> Low | U200: =$AE$193 -> Low | AD200: =Y347 -> Timing | AE200: =AB347 -> Low | AH200: =AE347 -> WFI/WFDU | AI200: =AH347 -> Low | AL200: =AK347 -> WFI/WFDU | AM200: =AN347 -> Low | AP200: =AQ347 -> WFI/WFDU | AQ200: =AT347 -> Good | AR200: =$AV$358 -> Assets and Utilities | AS200: =BJ340 -> Low
C201: =$X$342 -> Intense Precipitation | D201: =AE195 -> Low | L201: =AE196 -> Low | U201: =AE197 -> Low | AD201: =Y348 -> Intensity | AE201: =AB348 -> Low | AH201: =AE348 -> ATF/I | AI201: =AH348 -> Low | AL201: =AK348 -> ATF/I | AM201: =AN348 -> Low | AP201: =AQ348 -> ATF/I | AQ201: =AT348 -> Good | AR201: =$AV$371 -> Potable water | AS201: =BJ341 -> Low
C202: =$X$346 -> Droughts | D202: =AE199 -> Low | I202: =AE200 -> Low | Q202: =AE201 -> Low | X202: =AE202 -> Low | AD202: =Y349 -> Impact | AE202: =AB349 -> Low | AH202: =AE349 -> Disaster Events | AI202: =AH349 -> Low | AL202: =AK349 -> Disaster Events | AM202: =AN349 -> Low | AP202: =AQ349 -> Disaster Events | AQ202: =AT349 -> Good | AR202: =$AV$375 -> EBS | AS202: =BJ342 -> Low
C203: =$X$351 -> Flooding | D203: =$AE$204 -> Low | G203: =AE205 -> Low | M203: =AE206 -> Low | S203: =AE207 -> Low | X203: =AE208 -> Low | AB203: =" " | AC203: =X350 | AD203: =Y350 | AF203: =AC350 | AG203: =AD350 | AH203: =AE350 | AJ203: =AI350 | AR203: =$AV$386 -> Institutions | AS203: =BJ343 -> Low
C204: =$X$357 -> Flash Floods | D204: =AE210 -> Low | G204: =AE211 -> Low | M204: =AE212 -> Low | S204: =AE213 -> Low | X204: =AE214 -> Low | AB204: 4 | AC204: =X351 -> Flooding | AD204: =Y351 -> App or Freq | AE204: =AB351 -> Low | AF204: =AC351 -> 2 | AG204: =AD351 -> Health & Safety | AH204: =AE351 -> Borne Diseases | AI204: =AH351 -> Low | AJ204: =AI351 -> 2 | AK204: =AJ351 -> Health & Safety | AL204: =AK351 -> Borne Diseases | AM204: =AN351 -> Low | AN204: =AO351 -> 2 | AO204: =AP351 -> Health & Safety | AP204: =AQ351 -> Borne Diseases | AQ204: =AT351 -> Good
C205: =$X$363 -> Storms & Upper Winds | D205: =AE216 -> Low | L205: =AE217 -> Low | U205: =AE218 -> Low | AD205: =Y352 -> Timing | AE205: =AB352 -> Low | AH205: =AE352 -> SLUP&C | AI205: =AH352 -> Low | AL205: =AK352 -> SLUP&C | AM205: =AN352 -> Low | AP205: =AQ352 -> SLUP&C | AQ205: =AT352 -> Good | AR205: Current Vulnarability | AV205: Current Risk
C206: =$X$367 -> Pollution | D206: =AE220 -> Low | L206: =AE221 -> Low | U206: =AE222 -> Low | AD206: =Y353 -> Intensity | AE206: =AB353 -> Low | AH206: =AE353 -> SWM | AI206: =AH353 -> Low | AL206: =AK353 -> SWM | AM206: =AN353 -> Low | AP206: =AQ353 -> SWM | AQ206: =AT353 -> Good | AR206: =AF191 -> 1 | AS206: =AG191 -> Livelihoods | AT206: =AH191 -> Food Security | AU206: =AZ338 -> Low | AV206: =AS206 -> Livelihoods | AW206: =AT206 -> Food Security | AX206: =BF338 -> Low
C207: =$X$371 -> LUI | D207: =AE224 -> Low | L207: =AE225 -> Low | U207: =AE226 -> Low | AD207: =Y354 -> Extent | AE207: =AB354 -> Low | AH207: =AE354 -> LWM | AI207: =AH354 -> Low | AL207: =AK354 -> LWM | AM207: =AN354 -> Low | AP207: =AQ354 -> LWM | AQ207: =AT354 -> Good | AT207: =AH192 -> Grazing/Farm Land | AU207: =AZ339 -> Low | AW207: =AT207 -> Grazing/Farm Land | AX207: =BF339 -> Low
C208: =$X$375 -> Other Factors | D208: =AE228 -> Low | G208: =AE229 -> Low | K208: =AE230 -> Low | N208: =AE231 -> Low | Q208: =AE232 -> Low | X208: =AE233 -> Low | Y208: =AE234 -> Low | Z208: =AE235 -> Low | AD208: =Y355 -> Impact | AE208: =AB355 -> Low | AH208: =AE355 -> ATHS | AI208: =AH355 -> Low | AL208: =AK355 -> ATHS | AM208: =AN355 -> Low | AP208: =AQ355 -> ATHS | AQ208: =AT355 -> Good | AT208: =AH193 -> Crops | AU208: =AZ340 -> Low | AW208: =AT208 -> Crops | AX208: =BF340 -> Low
B209: EXPOSURE | AB209: =" " | AH209: =AE356 -> ATHE | AI209: =AH356 -> Low | AL209: =AK356 -> ATHE | AM209: =AN356 -> Low | AP209: =AQ356 -> ATHE | AQ209: =AT356 -> Good | AT209: =AH194 -> Livestock | AU209: =AZ341 -> Low | AW209: =AT209 -> Livestock | AX209: =BF341 -> Low
B210: =$AD$338 -> Livelihoods | C210: =AE338 -> Food Security | D210: =AE339 -> Grazing/Farm Land | F210: =AE340 -> Crops | H210: =AE341 -> Livestock | K210: =AE342 -> Fishstock | N210: =AE343 -> Local commerce | R210: =AE344 -> Gender | U210: =AE345 -> Conviviality | X210: =AE346 -> Education | Y210: =AE347 -> WFI/WFDU | Z210: =AE348 -> ATF/I | AA210: =AE349 -> Disaster Events | AB210: 5 | AC210: =X357 -> Flash Floods | AD210: =Y357 -> App or Freq | AE210: =AB357 -> Low | AF210: =AC357 | AG210: =AD357 | AH210: =AE357 | AJ210: =AI357 | AT210: =AH195 -> Fishstock | AU210: =AZ342 -> Low | AW210: =AT210 -> Fishstock | AX210: =BF342 -> Low
B211: =$AD$351 -> Health & Safety | C211: =AE351 -> Borne Diseases | D211: =AE352 -> SLUP&C | G211: =AE353 -> SWM | L211: =AE354 -> LWM | R211: =AE355 -> ATHS | Y211: =AE356 -> ATHE | AD211: =Y358 -> Timing | AE211: =AB358 -> Low | AF211: =AC358 -> 3 | AG211: =AD358 -> Assets and Utilities | AH211: =AE358 -> Housing | AI211: =AH358 -> Low | AJ211: =AI358 -> 3 | AK211: =AJ358 -> Assets and Utilities | AL211: =AK358 -> Housing | AM211: =AN358 -> Low | AN211: =AO358 -> 3 | AO211: =AP358 -> Assets and Utilities | AP211: =AQ358 -> Housing | AQ211: =AT358 -> Good | AT211: =AH196 -> Local commerce | AU211: =AZ343 -> Low | AW211: =AT211 -> Local commerce | AX211: =BF343 -> Low
B212: =$AD$358 -> Assets and Utilities | C212: =AE358 -> Housing | D212: =AE359 -> Public facilities | F212: =AE360 -> SWD | H212: =AE361 -> Sanitary facilities | K212: =AE362 -> Sewer lines | N212: =AE363 -> Power lines/supply | R212: =AE364 -> Energy for HH use | U212: =AE365 -> Water pipes | X212: =AE366 -> PWT | Y212: =AE367 -> Water Storage | Z212: =AE368 -> R & T | AA212: =AE369 -> Communication | AD212: =Y359 -> Intensity | AE212: =AB359 -> Low | AH212: =AE359 -> Public facilities | AI212: =AH359 -> Low | AL212: =AK359 -> Public facilities | AM212: =AN359 -> Low | AP212: =AQ359 -> Public facilities | AQ212: =AT359 -> Good | AT212: =AH197 -> Gender | AU212: =AZ344 -> Low | AW212: =AT212 -> Gender | AX212: =BF344 -> Low
B213: =$AD$371 -> Potable water | C213: =AE371 -> Access | J213: =AE372 -> Scarcities | X213: =AE373 -> Quality | AD213: =Y360 -> Extent | AE213: =AB360 -> Low | AH213: =AE360 -> SWD | AI213: =AH360 -> Low | AL213: =AK360 -> SWD | AM213: =AN360 -> Low | AP213: =AQ360 -> SWD | AQ213: =AT360 -> Good | AT213: =AH198 -> Conviviality | AU213: =AZ345 -> Low | AW213: =AT213 -> Conviviality | AX213: =BF345 -> Low
...

Sheet Responses
C5: According to the vulnerability and risk assessment, the following areas can be rated as high:
D7: CURRENT VULNERABILITY
D9: =C207 -> Livelihoods | F9: =E207 -> Health & Safety | I9: =I207 -> Assets and Utilities | M9: =O207 -> Potable water | P9: =V207 -> EBS | T9: =Z207 -> Institutions
D10: In more detail:
C11: =C212 -> Livelihoods | D11: =D212 -> Food Security | E11: =E212 -> Grazing/Farm Land | G11: =G212 -> Crops | I11: =I212 -> Livestock | L11: =L212 -> Fishstock | O11: =O212 -> Local commerce | S11: =S212 -> Gender | W11: =V212 -> Conviviality | Y11: =Y212 -> Education | Z11: =Z212 -> WFI/WFDU | AA11: =AA212 -> ATF/I | AB11: =AB212 -> Disaster Events
C12: =C213 -> Health & Safety | D12: =D213 -> Borne Diseases | G12: =E213 -> SLUP&C | L12: =H213 -> SWM | S12: =M213 -> LWM | Y12: =S213 -> ATHS | AA12: =Z213 -> ATHE
C13: =C214 -> Assets and Utilities | D13: =D214 -> Housing | E13: =E214 -> Public facilities | G13: =G214 -> SWD | I13: =I214 -> Sanitary facilities | L13: =L214 -> Sewer lines | O13: =O214 -> Power lines/supply | S13: =S214 -> Energy for HH use | W13: =V214 -> Water pipes | Y13: =Y214 -> PWT | Z13: =Z214 -> Water Storage | AA13: =AA214 -> R & T | AB13: =AB214 -> Communication
C14: =C215 -> Potable water | D14: =D215 -> Access | K14: =K215 -> Scarcities | Y14: =Y215 -> Quality
C15: =C216 -> EBS | D15: =D216 -> Soil | F15: =E216 -> LC & P | I15: =H216 -> NV | M15: =K216 -> Wetland | R15: =N216 -> Biodiversity | W15: =S216 -> NWB | Y15: =Y216 -> Sea | Z15: =Z216 -> EF | AA15: =AA216 -> Land use | AB15: =AB216 -> Topography
C16: =C217 -> Institutions | D16: =D217 -> EWS | F16: =E217 -> A & I | I16: =H217 -> EC | L16: =L217 -> R/RP | P16: =P217 -> HFO | X16: =W217 -> DP | Z16: =Z217 -> DR | AA16: =AA217 -> PFR | AB16: =AB217 -> PFM
D18: CURRENT RISK
D20: =C187 -> Livelihoods | F20: =E187 -> Health & Safety | I20: =I187 -> Assets and Utilities | M20: =O187 -> Potable water | P20: =V187 -> EBS | T20: =Z187 -> Institutions
D21: In more detail:
C22: =C192 -> Livelihoods | D22: =D192 -> Food Security | E22: =E192 -> Grazing/Farm Land | G22: =G192 -> Crops | I22: =I192 -> Livestock | L22: =L192 -> Fishstock | O22: =O192 -> Local commerce | S22: =S192 -> Gender | W22: =V192 -> Conviviality | Y22: =Y192 -> Education | Z22: =Z192 -> WFI/WFDU | AA22: =AA192 -> ATF/I | AB22: =AB192 -> Disaster Events
C23: =C193 -> Health & Safety | D23: =D193 -> Borne Diseases | G23: =E193 -> SLUP&C | L23: =H193 -> SWM | S23: =M193 -> LWM | Y23: =S193 -> ATHS | AA23: =Z193 -> ATHE
C24: =C194 -> Assets and Utilities | D24: =D194 -> Housing | E24: =E194 -> Public facilities | G24: =G194 -> SWD | I24: =I194 -> Sanitary facilities | L24: =L194 -> Sewer lines | O24: =O194 -> Power lines/supply | S24: =S194 -> Energy for HH use | W24: =V194 -> Water pipes | Y24: =Y194 -> PWT | Z24: =Z194 -> Water Storage | AA24: =AA194 -> R & T | AB24: =AB194 -> Communication
C25: =C195 -> Potable water | D25: =D195 -> Access | K25: =K195 -> Scarcities | Y25: =Y195 -> Quality
C26: =C196 -> EBS | D26: =D196 -> Soil | F26: =E196 -> LC & P | I26: =H196 -> NV | M26: =K196 -> Wetland | R26: =N196 -> Biodiversity | W26: =S196 -> NWB | Y26: =Y196 -> Sea | Z26: =Z196 -> EF | AA26: =AA196 -> Land use | AB26: =AB196 -> Topography
C27: =C197 -> Institutions | D27: =D197 -> EWS | F27: =E197 -> A & I | I27: =H197 -> EC | L27: =L197 -> R/RP | P27: =P197 -> HFO | X27: =W197 -> DP | Z27: =Z197 -> DR | AA27: =AA197 -> PFR | AB27: =AB197 -> PFM
C30: To view the responses required for each of the current and future high risk and high vulnerability areas, please click on this tab. This tab should also be clicked after any changes are made to the questionnaire. Once the tab has been clicked, please scroll below.
B35: CATEGORIES | F35: VULNERABILITY | L35: RISK | R35: ="Not High" -> Not High | S35: IN ORDER TO REDUCE VULNERABILITY AND RISK, YOU WOULD NEED TO IMPLEMENT THE FOLLOWING RESPONSE ACTIONS:
F36: CURRENT | L36: CURRENT | R36: High
B37: =RVAT_Output!$AV338 -> Livelihoods | R37: =IF(OR(R38=$R$36,R41=$R$36,R49=$R$36),$R$36,$R$35) -> Not High | S37: .
C38: =RVAT_Output!AW338 -> Food Security | F38: =RVAT_Output!AZ338 -> Low | L38: =RVAT_Output!BF338 -> Low | R38: =IF(OR(R39=$R$36,R42=$R$36,R50=$R$36),$R$36,$R$35) -> Not High | S38: PLANNING • Foresee adequate areas formally available to practice subsistence agriculture and keep livestock • Plan for land uses and accompanying programs that support diversification of livelihoods • Plan construction of abattoirs • Mitigate land use conversion of fertile soils, and assign appropriate sites for settlement growth ` | AA38: DESIGNS ` | AI38: COMMUNITY DEVELOPMENT PLANS • Foresee adequate areas formally available to practice subsistence agriculture, grazing areas, and livestock keeping • Plan storage facilities in commercial areas and markets • For settlements at risk of drought and extreme temperature, develop a mechanism to help stabilize livestock prizes and create markets for sale of livestock • Plan one-stop-centres for farmers `
C39: =RVAT_Output!AW339 -> Grazing/Farm Land | F39: =RVAT_Output!AZ339 -> Low | L39: =RVAT_Output!BF339 -> Low | R39: =IF(OR(R40=$R$36,R43=$R$36,R51=$R$36),$R$36,$R$35) -> Not High | S39: PLANNING • Foresee adequate areas formally available to practice subsistence agriculture, and grazing where this is part of livelihood of the community ` | AA39: DESIGNS ` | AI39: COMMUNITY DEVELOPMENT PLANS `
C40: =RVAT_Output!AW340 -> Crops | F40: =RVAT_Output!AZ340 -> Low | L40: =RVAT_Output!BF340 -> Low | R40: =IF(OR(R41=$R$36,R44=$R$36,R52=$R$36),$R$36,$R$35) -> Not High | S40: PLANNING • Foresee adequate areas formally available to practice subsistence agriculture • Identify risk zones and mark risky areas ` | AA40: DESIGNS ` | AI40: COMMUNITY DEVELOPMENT PLANS • Foresee a program to facilitate access to crop storage (MF) and water storage for irrigation • Program to improve / reinstate soil quality `
C41: =RVAT_Output!AW341 -> Livestock | F41: =RVAT_Output!AZ341 -> Low | L41: =RVAT_Output!BF341 -> Low | R41: =IF(OR(R42=$R$36,R45=$R$36,R53=$R$36),$R$36,$R$35) -> Not High | S41: PLANNING • Identify risk zones and mark risky areas • Foresee adequate areas for livestock keeping if applicable; in arid regions facilitate nomadic animal husbandry ` | AA41: DESIGNS ` | AI41: COMMUNITY DEVELOPMENT PLANS • Foresee a program to facilitate access to water storage for livestock • Consider incentives for nomadic animal husbandry in arid regions, in combination with respective land use planning `
C42: =RVAT_Output!AW342 -> Fishstock | F42: =RVAT_Output!AZ342 -> Low | L42: =RVAT_Output!BF342 -> Low | R42: =IF(OR(R43=$R$36,R46=$R$36,R54=$R$36),$R$36,$R$35) -> Not High | S42: PLANNING • Identify risk zones and mark risky areas ` | AA42: DESIGNS ` | AI42: COMMUNITY DEVELOPMENT PLANS `
C43: =RVAT_Output!AW343 -> Local commerce | F43: =RVAT_Output!AZ343 -> Low | L43: =RVAT_Output!BF343 -> Low | R43: =IF(OR(R44=$R$36,R47=$R$36,R55=$R$36),$R$36,$R$35) -> Not High | S43: PLANNING • Identify location-based opportunities for LED, including in the low carbon economy; Facilitate diverse economic opportunities by allowing small business unit sizes, plan for mixed use areas; • Identify risk zones and mark risky areas • Consider safe conditions for economic growth in land use and infrastructure planning • Facilitate diverse economic opportunities by allowing small business unit sizes, plan for mixed use areas; ` | AA43: DESIGNS ` | AI43: COMMUNITY DEVELOPMENT PLANS `
C44: =RVAT_Output!AW344 -> Gender | F44: =RVAT_Output!AZ344 -> Low | L44: =RVAT_Output!BF344 -> Low | R44: =IF(OR(R45=$R$36,R48=$R$36,R56=$R$36),$R$36,$R$35) -> Not High | S44: PLANNING • Adopt gender-responsive planning processes • Ensure reflection of climate risk- and gender- responsive investments • Identify gender vulnerabilities as part of the strengthened existing conditions assessment • Design safe spaces ` | AA44: DESIGNS • Respond to gender-based needs in designs of infrastructures • Design safe facilities ` | AI44: COMMUNITY DEVELOPMENT PLANS • Respond to gender-differentiated needs in designs of public facilities and programs • Integrate gender in all County decision-making processes • Ensure that programs for access to micro finance -, skills development or access to health care, are gender sensitive • avail critical facilities during disasters considering gender-differentiated needs. `
C45: =RVAT_Output!AW345 -> Conviviality | F45: =RVAT_Output!AZ345 -> Low | L45: =RVAT_Output!BF345 -> Low | R45: =IF(OR(R46=$R$36,R49=$R$36,R57=$R$36),$R$36,$R$35) -> Not High | S45: PLANNING • Foresee adequate grazing and farming areas for the population size • Foresee well-designed, well accessible, and safe public spaces even if small ` | AA45: DESIGNS • Integrate public lighting and shading in public space ` | AI45: COMMUNITY DEVELOPMENT PLANS • Create awareness about the potential triggers that may cause climate related conflict and how to mitigate disputes before they escalate • Identify causes of dispute and plan for program for dispute resolution `
C46: =RVAT_Output!AW346 -> Education | F46: =RVAT_Output!AZ346 -> Low | L46: =RVAT_Output!BF346 -> Low | R46: =IF(OR(R47=$R$36,R50=$R$36,R58=$R$36),$R$36,$R$35) -> Not High | S46: PLANNING • Make provisions to protect schools from severe weather events and make accessible at all times • place schools in safe and well accessible locations, where newly planned ` | AA46: DESIGNS • foresee protective measures that ensure resiliency (adequate drainage, infiltration) ` | AI46: COMMUNITY DEVELOPMENT PLANS • Ensure access to water, sanitation and school feeding services at school • Ensure access to water and electricity, and budget for and equip with generators and water tanks • Prepare mechanism that will preposition books and writing material and develop a mechanism for their distribution in case of disaster • As part of the SOPs, prepare a mechanism for safe evacuation of teachers and children • Prepare a mechanism with the County that will ensure access to always water and sanitation services at school `
C47: =RVAT_Output!AW347 -> WFI/WFDU | F47: =RVAT_Output!AZ347 -> Low | L47: =RVAT_Output!BF347 -> Low | R47: =IF(OR(R48=$R$36,R51=$R$36,R59=$R$36),$R$36,$R$35) -> Not High | S47: PLANNING • Where the climate risk is drought, undertake hydrological study as part of existing conditions analysis ` | AA47: DESIGNS • Foresee boreholes in low lying areas ` | AI47: COMMUNITY DEVELOPMENT PLANS • Foresee a program to facilitate access to water storage • Identify and promote local resilient crops for subsistence farming • Foresee desalination measures on irrigated land in drought prone regions (drainage) to maintain soil fertility • Develop rotational irrigation system with all farming community members • Consider feasibility of desalination plant in arid, coastal regions `
C48: =RVAT_Output!AW348 -> ATF/I | F48: =RVAT_Output!AZ348 -> Low | L48: =RVAT_Output!BF348 -> Low | R48: =IF(OR(R49=$R$36,R52=$R$36,R60=$R$36),$R$36,$R$35) -> Not High | S48: PLANNING ` | AA48: DESIGNS ` | AI48: COMMUNITY DEVELOPMENT PLANS • Facilitate and promote enrolment in disaster insurance program • Prepare a mechanism for cash for asset programs and / or cash for work programs • Prepare a mechanism to ensure access to finance, e.g. for SME’s and farmers to bridge interim income losses • Prepare a mechanism for access to finance for women’s groups `
C49: =RVAT_Output!AW349 -> Disaster Events | F49: =RVAT_Output!AZ349 -> Low | L49: =RVAT_Output!BF349 -> Low | R49: =IF(OR(R50=$R$36,R53=$R$36,R61=$R$36),$R$36,$R$35) -> Not High | S49: PLANNING • Plan water retention ponds • Plan for ecosystem restoration projects ` | AA49: DESIGNS ` | AI49: COMMUNITY DEVELOPMENT PLANS • Plan for storm water collection at public facilities, markets etc • For Community Disaster Risk Management Plans (CDRMP), the following content should at least be addressed: 1. Early warning system and communication 2. Awareness and information 3. Actors 4. Critical infrastructure 5. Evacuation and evacuation shelter 6. Health services 7. Food security 8. Maintained education 9. Maintained livelihood/ 10. HH income • There shall be an Evacuation Plan for the community including Standard Operational Procedures (SOPs) elaborated, which includes: Evacuation routes, Identified mapped critical assets / o Measures proposed to safeguard the critical assets (and to plan for their implementation, Identified evacuation shelter, Actors with assigned responsibilities / Awareness and information programs `
B50: =RVAT_Output!$AV351 -> Health & Safety | R50: =IF(OR(R51=$R$36,R54=$R$36,R62=$R$36),$R$36,$R$35) -> Not High | S50: .
C51: =RVAT_Output!AW351 -> Borne Diseases | F51: =RVAT_Output!AZ351 -> Low | L51: =RVAT_Output!BF351 -> Low | R51: =IF(OR(R52=$R$36,R55=$R$36,R63=$R$36),$R$36,$R$35) -> Not High | S51: ` | AA51: ` | AI51: COMMUNITY DEVELOPMENT PLANS • Foresee reinstatement and enhancement of vegetative cover • Foresee measures with the objective of improving water quality of rivers, where applicable (awareness and information) • Foresee promotion of rainwater harvesting through awareness campaigns and facilitation of access to finance for rainwater storage and private households • Foresee accompanying programs that facilitate micro finance for access to water tanks that will contribute to securing access to water during dry periods • Establish programs that provides advice on private improvement to homes to reduce climate vulnerabilities at individual household level • Foresee sufficient number of water extraction points for maximum extraction for every identified water source to not exceed natural recharge • Foresee provisions to ensure availability of sufficient quantities of water in dry seasons and during interrupted water supply by installing sufficient water storage and ensure timely filling in conjunction with the water authorities • foresee water and rainwater tanks for public facilities managed under the Counties • foresee sunshades and tree planting of indigenous species • increased number of boreholes • ground water recharge measures • Protection measures for ground water extraction points from pollution Consider different responses depending on gender and age `
C52: =RVAT_Output!AW352 -> SLUP&C | F52: =RVAT_Output!AZ352 -> Low | L52: =RVAT_Output!BF352 -> Low | R52: =IF(OR(R53=$R$36,R56=$R$36,R64=$R$36),$R$36,$R$35) -> Not High | S52: PLANNING • Identify risk zones and mark risky areas • Where the hazard risk is intense precipitation and floods, ensure that sanitary facilities are located outside of floodplains, flash flood pathways, and completely above ground water table • Undertake careful siting of industries to prevent vulnerability to air pollution in consideration of wind directions • Require natural permeable areas in support of storm water infiltration and in response to storm water flow paths • Where the hazard risk is intense precipitation and floods sanitary facilities must be located outside of floodplains, flash flood pathways, and be completely above ground water table • foresee investment in ecosystem restoration, development of ecosystem services, afforestation and agroforestry. • Improve soil properties and vegetative cover through measures in support of grazing, groundwater rechange • Rebuild natural protective features, such as vegetative cover and specifically mangrove forests in coastal areas • Identify risk zones and mark risky areas for their further exclusion from building development/urbanisation and address in intense consultative process (for guidelines see 3.1.3) • ensure all weather access to health facilities within a safe location and standard distance from any point in the settlement, and consider universal accessibilities for all, regardless of gender, age, social group, ability etc. • identify appropriate sanitation system to be supported in conjunction with water availabilities for stocktaking by design consultants and advise on the risk of foreseeing a sewer system if identified as unfeasible • Identify and map out high-risk zones within the settlement • Identify the affected households • Identify interventions that may reduce the risk, such as increasing vegetative cover, increasing infiltration areas etc • Identify options of physical correction in the private realm and train residents ` | AA52: DESIGNS • Maximize natural infiltration area, increase vegetative cover, assess feasibility of storm water retention depending on the site and location, verify options of improving natural embankment stabilization • There shall be no siting of new roads in wetlands and flood prone zones • Vegetative soil stabilization measures shall be adopted in conjunction with road network planning and storm water management planning • Road designs must provenly ensure that any new paved areas and roadways do not cause an unacceptable rise in groundwater on adjacent sites, especially in areas with high ground water tables. • Plan for slopes to be well covered with deep rooted vegetation • Ensure adequate road surface drainage measures to move water off the road surface rapidly and prevent the accumulation of water. • Take measures to ensure immediate pulling back of marginally unstable or failing sliver fill slopes. ` | AI52: COMMUNITY DEVELOPMENT PLANS `
C53: =RVAT_Output!AW353 -> SWM | F53: =RVAT_Output!AZ353 -> Low | L53: =RVAT_Output!BF353 -> Low | R53: =IF(OR(R54=$R$36,R57=$R$36,R65=$R$36),$R$36,$R$35) -> Not High | S53: PLANNING • The SWM plan must align with the LPLUDP and the below aspects coordinated with the planning process and content. • Location of landfill, waste collection points and waste collection and transportation routes • Landfill locations must consider the surface topography, subsurface and hydrogeological conditions • Landfills must not be sited o on land used for a water supply system;/o within a flood area, flood plain, or wetland;/o within dam failure;/o in any location that could cause water contamination, including the water of a lake, reservoir, or pond/o within a subsistence agriculture area;/o above an underground mine;/o above a fault;/o above a salt bed;/o near other geologic features which could compromise structural integrity;/o within an area of volcanic hazard. • Landfills locations must exceed a distance of o 400 m from residential, commercial and public buildings;/o 1,000 m from a river bank;/o 400 m from a water source;/o 300 m from a park, monument, recreation area, ecologically significant area, farmland area, or in “prime”, “unique”, or of “government wide importance” area;/o 400 m from a burial site;/o 3,000 m from an airport runway; • Assign safe areas to animal husbandry ` | AA53: DESIGNS • Existing landfills/waste disposal sites that will be used as part of the SWM scheme must be screened for climate impacts. The result must be presented as part of the SWM plan report. ` | AI53: COMMUNITY DEVELOPMENT PLANS • Sensitization program on avoid – reuse – recycle for reduction of landfill amounts • Separation of organic matter to divert organic matter from landfills and promote composting • Plan for composting, or bio digester system to recover methane from organic waste as energy source, where feasible and in combination with livestock faming • Include planning for composting trainings • Include program to provide separate bins to enable waste separation • Keep bridge channels cleared and free of excessive debris. • Keep culverts in good condition, free of debris, and with version prevention measures installed. • Respect the below guidelines for waste collection points: Separate and sufficiently large bins must be foreseen to enable waste separation; Waste separation and recycling activities shall be co-located; Waste collection points must be located away from direct runoff zone of a river or stream; Consider green finance incentives to incentivise waste separation through separate bins (to be integrated with the SWM plans) `
B54: p8 | C54: =RVAT_Output!AW354 -> LWM | F54: =RVAT_Output!AZ354 -> Low | L54: =RVAT_Output!BF354 -> Low | R54: =IF(OR(R55=$R$36,R58=$R$36,R66=$R$36),$R$36,$R$35) -> Not High | S54: PLANNING ` | AA54: DESIGNS • In areas with shallow water table use elevated composting toilets • For decentralised sewage treatment solutions, consider low energy options such as reed beds, if feasible, and solutions with anaerobic digestion with capture and reuse of the methane • Foresee provisions to treat grey water before release into the environment ` | AI54: COMMUNITY DEVELOPMENT PLANS • There shall be solutions provided that help treat grey water from households to mitigate clogging from soap and grease and thus amplification of risk of flooding, by maintaining the natural infiltration capacity of soil • For any pit latrines located in flood plains, plan for their eventual replacement (e.g. elevated ecosan toilets, or relocation outside of the flood plain) • Consider green finance incentives to incentivise on-site wastewater treatment to the Kenya discharge standards • Integrate investment in bio-centres in the settlements for energy sources from animal and human organic wastes and faeces `
C55: =RVAT_Output!AW355 -> ATHS | F55: =RVAT_Output!AZ355 -> Low | L55: =RVAT_Output!BF355 -> Low | R55: =IF(OR(R56=$R$36,R59=$R$36,R67=$R$36),$R$36,$R$35) -> Not High | S55: PLANNING • Foresee siting of health facilities in safe locations Consider different needs depending on gender, age and abilities ` | AA55: DESIGNS • Foresee protective measures that ensure resiliency of the facilities (adequate drainage, infiltration, access to water and electricity, budget for and equip with generators and water tanks, etc) ` | AI55: COMMUNITY DEVELOPMENT PLANS • Plan for measures that protect the health facilities from identified flash flood flow paths and hydrological conditions during flood and intense precipitation • Budget for sufficient personnel, equipment and resources for the local health facilities • Train community members in first aid • Help ensuring enrolment in national health insurance fund (NHIF) Consider different needs depending on gender, age and abilities `
C56: =RVAT_Output!AW356 -> ATHE | F56: =RVAT_Output!AZ356 -> Low | L56: =RVAT_Output!BF356 -> Low | R56: =IF(OR(R57=$R$36,R60=$R$36,R68=$R$36),$R$36,$R$35) -> Not High | S56: PLANNING • Integrate nature and adapt to natural conditions features, and reinstate where applicable ` | AA56: DESIGNS • Plan for measures to safeguard groundwater, landfill sites and sewage treatment sites to control pollution • Comply with the objectives of minimizing GHG minimization in the whole value chain of the works • Mitigate soil, water and crops pollution from sewer/pit overflows and other hazardous materials • Line landfills and waste collection points ` | AI56: COMMUNITY DEVELOPMENT PLANS • Plan for measures to safeguard pit latrines and septic tanks from overflow and spilling of faeces into the environment • For any pit latrines located in flood plains, plan for their eventual replacement (e.g. elevated ecosan toilets, or relocation outside of the flood plain) • Undertake awareness, information and enforcement options of environmental regulations to sensitize, audit and make accountable large-scale industries on illegal pollution and discharges into the environment/water bodies • Awareness, information and enforcement shall also include environmental regulations, particularly with the help of National and County governments, to sensitize and audit large scale industries on illegal pollution and discharges into the environment/water bodies. • Facilitate finance programs for upgrading of industrial technologies to mitigate pollution • Foresee sensibilization, awareness programs coupled with identification and servicing of safe settlement sites • Consider investment in sites and services projects where feasible • Initiate / facilitate micro finance programs that encourage replacement of domestic and commercial use of high emission fuels `
B57: =RVAT_Output!$AV358 -> Assets and Utilities | R57: =IF(OR(R58=$R$36,R61=$R$36,R69=$R$36),$R$36,$R$35) -> Not High | S57: .
C58: =RVAT_Output!AW358 -> Housing | F58: =RVAT_Output!AZ358 -> Low | L58: =RVAT_Output!BF358 -> Low | R58: =IF(OR(R59=$R$36,R62=$R$36,R70=$R$36),$R$36,$R$35) -> Not High | S58: PLANNING • Safeguard critical assets and utilities part of the planning process • Locate any new critical assets and utilities outside of high-risk zones • Ensure minimum accessibility of the settlement accessible in all weather conditions (access to/and within) for emergency vehicles and public transport; ` | AA58: DESIGNS N/A to KISIP ` | AI58: COMMUNITY DEVELOPMENT PLANS • Establish programs that provide advice to private improvement to homes to reduce climate vulnerabilities at individual household level • Consider green finance incentives to incentivise climate change mitigation measures in private investment on residential and commercial buildings, for example: Use of reflective roofing for reduction of heat island effect; On-site wastewater treatment to the Kenya discharge standards; For new construction, incentivised building design that minimizes heat gain and facilitates good natural ventilation with layouts that utilizes prevailing wind conditions to ensure cross ventilation • Create awareness and disseminate information on green building and building appliances Consider different needs depending on gender, age and abilities `
C59: =RVAT_Output!AW359 -> Public facilities | F59: =RVAT_Output!AZ359 -> Low | L59: =RVAT_Output!BF359 -> Low | R59: =IF(OR(R60=$R$36,R63=$R$36,R71=$R$36),$R$36,$R$35) -> Not High | S59: PLANNING • Map out hazardous areas and the effected households, and address risk and vulnerability reduction as part of the planning process through various means; consider flash flood flow paths in conjunction with clayey soils as risk areas • Ensure safe location • Ensure all weather access and universal accessibility • foresee water and rainwater tanks for public facilities not to be settled • Ensure storm water flows are fully planned and managed from source up to outlet; • Ensure minimum accessibility of the facility accessible in all weather conditions (access to/and within) for emergency vehicles and public transport; • Foresee natural infiltration areas within the plans and designs by foreseeing open space ponds and ecological basins ` | AA59: DESIGNS • Assess storm water flow path • Maximize natural infiltration area, increase vegetative cover, assess feasibility of storm water retention depending on the site and location, verify options of improving natural embankment stabilization • Treat as an integral part within storm water management planning process ` | AI59: COMMUNITY DEVELOPMENT PLANS • In areas at risk of drought foresee rain water storages for public facilities managed under the Counties • In areas with intense precipitation, combine infiltration measures with rain water collection Consider different responses depending on gender, age and abilities `
C60: =RVAT_Output!AW360 -> SWD | F60: =RVAT_Output!AZ360 -> Low | L60: =RVAT_Output!BF360 -> Low | R60: =IF(OR(R61=$R$36,R64=$R$36,R72=$R$36),$R$36,$R$35) -> Not High | S60: PLANNING • The plans must consider existing land uses and surface characteristics, and those planned with the new agreed interventions. In addition, a plan shall be provided showing future expansion requirements in conjunction with the entire LPLUDP and CDP where available, including such changes that will not yet be implemented under KISIP2. • The analysis method and choice of parameters and other inputs must be replicable, including flood frequencies and flow velocities • The resiliency of the design shall be proven, for example by calculating a variety of scenarios and by comparing with results from nearby locations if possible • The reports and plans must be provided to enable the evaluation committee to reproduce the results, including all input values and methods of modelling • In areas at risk of flooding and intense precipitation, LPLUDP’s must provenly consider and reflect the results of geological and hydrological assessments. • consider flash flood flow paths in conjunction with clayey soils as risk areas not to be settled • Ensure storm water flows are fully planned and managed from source up to outlet • Foresee natural infiltration areas within the plans and designs by foreseeing open space ponds and ecological basins • In areas with intense precipitation: Combine infiltration measures with rain water collection; Preserve natural vegetation and other areas that filter runoff and reduce erosion • Where drainages are introduced, they must be fully planned and addressed from source up to outlet; there should be natural infiltration areas foreseen within the plans and designs by foreseeing open space ponds and ecological basins; ` | AA60: DESIGNS • For drainage construction, ensure use of locally available material and such masonry to reduce or eliminate demand on base material. • Storm water designs must consider drainage outlets and their surroundings and demonstratedly identify the optimum design parameters • Adopt nature-based solutions that protect and restore ecosystems and increase resiliency, denitrify surface runoff, making use of on-site natural features; • Maximize the opportunities for natural infiltration and manage stormwater runoff instead of managing storm water at source and draining it into sewers. • Foresee reinstatement of a hydrologic regime of catchments shall be by means of infiltrating, filtering, storing, evaporating, and detaining runoff close to its source. o The climate resilient scheme shall design permeable surfaces wherever possible. o Practical examples of green infrastructure include bioswales, permeable pavement, green roofs, rainwater tanks and public parks. • When designing transportation drainage systems, the designs must be based on assessment of: potential flooding caused by changes in water surface profiles, disturbance of the river system upstream or downstream of the intervention, changes in lateral flow distributions, changes in velocity or direction of flow, need for conveyance and disposal of excess runoff, need for channel linings to prevent erosion. • The designs supporting storm water management must consider: The existing land uses and surface characteristics, and those planned with the interventions, The runoff from all existing adjacent areas, The drainage outlets and their surroundings and demonstratedly identify the optimum design parameters, The future planned road upgrading measures, including change of surfaces, and any increase of impervious cover, which will influence increases storm water volume and velocity, Maximization of natural infiltration areas within the plans and designs by foreseeing open space ponds and ecological basins, Stream modification, such as realignment or relocation must not be permitted. • Where modifications have taken place in the past, natural conditions shall be reinstated as far as feasible as part of the LPLUDP proposal. The planning and design measures shall target enhanced water quality standards, measures that will mitigate heavy debris discharge and riverbank erosion and protect fish and wildlife resources. • Assume an annual exceedance probability (AEP) of at least 70 % in storm water management planning and designs; • Where there are large areas of paved surfaces, impermeable soils and steep slopes, retention ponds shall be used. ` | AI60: COMMUNITY DEVELOPMENT PLANS • Foresee measures that denitrify surface runoff • Foresee measures that prevent debris to enter into natural water bodies and ground water • Incentivize plot level water harvesting `
C61: =RVAT_Output!AW361 -> Sanitary facilities | F61: =RVAT_Output!AZ361 -> Low | L61: =RVAT_Output!BF361 -> Low | R61: =IF(OR(R62=$R$36,R65=$R$36,R73=$R$36),$R$36,$R$35) -> Not High | S61: PLANNING • Leachate fields and soakaways must not be placed in areas with regular high rainfall • Pit latrines must be completely above the water table ` | AA61: DESIGNS • Where the hazard risk is intense precipitation and floods, sanitary facilities must not be sited within floodplains, flash flood pathways, and completely above ground water table (Sanitation facilities, sewer lines, waste water treatment sites including septic tanks, pit latrines and soil absorption systems for effluent must not be located in flood plains and areas where the water table is higher than 2 m below ground) • The design of sanitation facilities must respect ground water protection by being located outside of floodplains, flash flood pathways, and completely above ground water table; and by being located at least 100 m away from ground water extraction points; relocate any pit latrines that are at risk of submerging in flood plains; • In areas with shallow water table use elevated composting toilets Consider different needs depending on gender, age and abilities ` | AI61: COMMUNITY DEVELOPMENT PLANS • Promote domestic grey water treatment solutions to mitigate soil clogging and amplified risk of flooding and to ensure natural soil infiltration capacity • Promote plant based domestic/or decentral or grey-water treatment system (mini reed bed) Low-cost greywater treatment for households Consider different responses depending on gender, age and abilities `
C62: =RVAT_Output!AW362 -> Sewer lines | F62: =RVAT_Output!AZ362 -> Low | L62: =RVAT_Output!BF362 -> Low | R62: =IF(OR(R63=$R$36,R66=$R$36,R74=$R$36),$R$36,$R$35) -> Not High | S62: PLANNING • Ensure minimum distance of 15 m of any sewer line to potable water exit points; ensure horizontal separation of water mains and sewers, with sewers always located below water mains • Siting of new sewer lines and other infrastructure in floodplains must be avoided ` | AA62: DESIGNS • Minimum distance of 15 m of any sewer line to potable water exit points must be ensured • Horizontal separation of water mains and sewers must be ensured, with sewers always located below water mains • Ensure fully adapted design of sewers based on a demand study (identifying all sewerage intakes) and water supply study and consultations with water board; evidence of the demand study shall be provided; possibly do not plan for sewer lines in areas at risk of drought and where there are water scarcities • In areas with high groundwater table, or in flood prone conditions, conventional gravity sewers must not be used • Where the hazard risk is drought, sewers must be designed to achieve self-cleaning velocity a peak flow, and sufficiency of water supply to the connected toilets must be ensured, or use of sewers be reconsidered and alternative sanitation solutions be prioritized • If sewer connection is not feasible or viable, foresee harvesting energy from methane from human and animal faeces where feasible ` | AI62: COMMUNITY DEVELOPMENT PLANS `
C63: =RVAT_Output!AW363 -> Power lines/supply | F63: =RVAT_Output!AZ363 -> Low | L63: =RVAT_Output!BF363 -> Low | R63: =IF(OR(R64=$R$36,R67=$R$36,R75=$R$36),$R$36,$R$35) -> Not High | S63: PLANNING • In areas at risk of storms consider underground power supply where feasible, however not in floodplains ` | AA63: DESIGNS • Foresee safety measures against electric shock Public lighting • For street lighting elements, ensure its longevity to reduce LED waste that is currently not recyclable and to reduce the negative environmental impact in sourcing the rare minerals in solar panels, where solar lamps are planned • For poles, ensure use of timber from sustainable commercial forestry in the design specifications • Apply solar power options, or from grid, where known to be generated from a green mix (which is the case in Kenya with 80% geothermal/ hydro/ wind) • Plan for low street lights instead of flood lights at least in settlements that are located in proximity to natural areas to minimize disturbance of wildlife ` | AI63: COMMUNITY DEVELOPMENT PLANS • Foresee lightning conductors on public buildings `
C64: =RVAT_Output!AW364 -> Energy for HH use | F64: =RVAT_Output!AZ364 -> Low | L64: =RVAT_Output!BF364 -> Low | R64: =IF(OR(R65=$R$36,R68=$R$36,R76=$R$36),$R$36,$R$35) -> Not High | S64: PLANNING ` | AA64: DESIGNS ` | AI64: COMMUNITY DEVELOPMENT PLANS • Create awareness and disseminate information on green building and building appliances o Include program aspect that promotes natural or artificial ventilation, lighting, and solar heat gains in the applicable regions o Include program aspect that promotes use of renewable energies o Promote green appliances for domestic use, e.g. by providing access to green (micro-)finance o Foresee measures to reduce demand on charcoal to preserve indigenous forests. • Consider green finance incentives to incentivise climate change mitigation measures in private investment on residential and commercial buildings, for example: o Roof installation for solar thermal or solar PV appliances (e.g. with points to be gained per total exposed roof area) o Use of reflective roofing for reduction of heat island effect o Off-grid renewable energy generation o Use of low wattage (energy saving) light bulbs o Use of eco jiko to reduce demand on charcoal. Eco jiko can also apply other domestic wastes for energy generation (heat), among other o For new construction, incentivised building design that minimizes heat gain and facilitates good natural ventilation with layouts that utilizes prevailing wind conditions to ensure cross ventilation `
C65: =RVAT_Output!AW365 -> Water pipes | F65: =RVAT_Output!AZ365 -> Low | L65: =RVAT_Output!BF365 -> Low | R65: =IF(OR(R66=$R$36,R69=$R$36,R77=$R$36),$R$36,$R$35) -> Not High | S65: PLANNING • Design for a resilient water supply system by making provisions for water supply and delivery; water quality; and water quality, based on a thorough existing conditions assessment as well as demand study. • Siting of underground water pipes shall not be in unstable soils • Siting of water pipes in flood plains must be avoided • Siting of water pipes near soil extraction sites must be avoided • The water supply planning shall be watershed based and use gravity flows ` | AA65: DESIGNS • In areas prone to drought, water pipes need protection against breakage or must be sited above ground, depending on feasibility study • Any design must respond to the water availability besides demand, and make provisions accordingly. • Closely engage and confirm the designs with the local water boards and present confirmed solutions regarding water supply capacity requirements • Take into account integration with water demand for the case where sewerage systems are proposed as part of the design and equally confirm with the responsible authority ` | AI65: COMMUNITY DEVELOPMENT PLANS • Foresee awareness campaigns against vandalism, and public protection measures • Siting of water pipes in flood plains must be avoided. • Siting of water access points in flood plains must not be undertaken. • Take measures to prevent sedimentation • Create vegetative barriers to prevent debris from flushing onto water bodies • Take measures to prevent spilling of water on unstable slopes from leaking pipes or other causes • Foresee measures to prevent pollution of fresh water bodies and water extraction points from debris / floatsome and effluent discharge associated with storm and wind surges • Prevent water pollution from debris / floatsome and effluent discharge `
C66: =RVAT_Output!AW366 -> PWT | F66: =RVAT_Output!AZ366 -> Low | L66: =RVAT_Output!BF366 -> Low | R66: =IF(OR(R67=$R$36,R70=$R$36,R78=$R$36),$R$36,$R$35) -> Not High | S66: PLANNING ` | AA66: DESIGNS • Plan for measures to safeguard groundwater, landfill sites and sewage treatment sites to control pollution ` | AI66: COMMUNITY DEVELOPMENT PLANS • potable water exit points must be safeguarded from pollution and destruction `
C67: =RVAT_Output!AW367 -> Water Storage | F67: =RVAT_Output!AZ367 -> Low | L67: =RVAT_Output!BF367 -> Low | R67: =IF(OR(R68=$R$36,R71=$R$36,R79=$R$36),$R$36,$R$35) -> Not High | S67: PLANNING • In areas with intense precipitation, combine infiltration measures with rain water collection; • Consider use of swales for natural water storage ponds where feasible ` | AA67: DESIGNS • Consider feasibility of combining storm water evacuation with water harvesting ` | AI67: COMMUNITY DEVELOPMENT PLANS • Foresee storages for water and food in markets and commercial areas • Foresee micro finance program that enables access to water tanks for private households and SMEs • Foresee water tanks on public facilities `
C68: =RVAT_Output!AW368 -> R & T | F68: =RVAT_Output!AZ368 -> Low | L68: =RVAT_Output!BF368 -> Low | R68: =IF(OR(R69=$R$36,R72=$R$36,R80=$R$36),$R$36,$R$35) -> Not High | S68: PLANNING • Ensure minimum accessibility of the settlement accessible in all weather conditions (access to/and within) for emergency vehicles and public transport; in areas with high temperature fluctuations avoid road construction and embankments on steep slopes; avoid major infrastructure construction and road network increase on clayey soils and hilly terrain • Natural ecosystems must be considered when planning for the objectives of transportation, mobility and commerce, and maximize the natural habitat forming processes while achieving hydraulic goals, such as flow routing, floodplain connectivity. • There shall be consideration of minimum accessibility of the settlement accessible in all weather conditions (access to/and within) for emergency vehicles and public transport; in heat prone areas, do not foresee asphalt paving; in areas with high temperature fluctuations avoid road construction and embankments on steep slopes; avoid major infrastructure construction and road network increase on clayey soils and hilly terrain • Plan for good and safe walkability and prioritize pedestrian movements within the settlement over vehicular movement. • Public and non-motorized modes of transport must be facilitated and prioritized • All year access to the settlement must demonstratedly be ensured, based on the existing conditions assessment that includes hazard risks • No new roads or road upgrading must be foreseen on/in saturated soils, highly erodible soils, slopes steeper than 60o riparian corridors and flood plains upslope from flood plains in narrow canyons • Road upgrading must be planned in a way to minimize/ avoid cutting down of trees in the road corridor. • Combine vegetative soil stabilization measures with adaptive road network planning and storm water management planning; minimize road network density; minimize road network on steep terrain • Natural systems must be considered when planning for the objectives of transportation, mobility and commerce, and maximize the natural habitat forming processes while achieving hydraulic goals, such as flow routing, floodplain connectivity. • Plan for good and safe walkability and prioritize pedestrian movements within the settlement over vehicular movement. There shall be adequate consideration of the need of safe and demand-oriented Non-Motorized Transport (NMT) o Promote walking and cycling though urban design and sufficient area and safety provisions • Program public transport service points with County. • All year access to the settlement must demonstratedly be ensured, based on the existing conditions assessment that includes hazard risks ` | AA68: DESIGNS • Geological assessments must be provenly considered, and the dependency of engineered infrastructures on embankments and retaining walls shall be minimized • Where new roads and / or road paving is introduced penetration of increasing motorized traffic and transport into the settlements is likely, and must be combined with speed control and promotion of public and non-motorized modes of transport. o Aspects of traffic congestions, parking problems, delivery problems, speeding must demonstratedly be addressed. • Where new roads and / or road paving is foreseen, the changed traffic demand caused by the intervention must be considered in the designs, including also demand for parking and goods delivery zones. • Where new roads and / or road paving is foreseen, there must demonstratedly be consideration of pedestrian safety measures, including but not limited to speed bumps, safe road crossings near schools, safe play areas, wide footpaths, etc. • Adapted road standard design shall not allow for all functions within smaller road widths, instead reduction of road functions in small road widths (in small road reserves, the number of road lanes cannot fulfil standard) • Road siting must demonstrably consider the hydrological and topographical conditions and siting of new roads in wetlands and flood prone zones must be avoided. • Road designs must provenly consider hydro-morphological alterations and future pressures from other newly planned infrastructure and other changes, which may impact the status of surface waters. • Road designs must provenly ensure that any new paved areas and roadways do not cause an unacceptable rise in groundwater on adjacent sites, especially in areas with high ground water tables. • Specify road pavement options that can be implemented through labour intensive methods • Use cobble stone where feasible (for purposes of safety, LED and reduced embedded GHG emission) • Apply such technologies and methods, which can easily be repaired by local people/ SME’s • For asphalt concrete paving, where not to be avoided, use warm and cold mix technologies (i.e. asphalt concreting production at considerably reduced temperatures) • Select materials and technologies that allow for reuse and recycling ` | AI68: COMMUNITY DEVELOPMENT PLANS • Tree lining of roads and public transportation hubs shall be foreseen • Public transportation hubs shall be shaded • Promote walking and cycling though urban design and sufficient area and safety provisions • Program public transport service points with County • Foresee (access to) road maintenance budget and inspections `
C69: =RVAT_Output!AW369 -> Communication | F69: =RVAT_Output!AZ369 -> Low | L69: =RVAT_Output!BF369 -> Low | R69: =IF(OR(R70=$R$36,R73=$R$36,R81=$R$36),$R$36,$R$35) -> Not High | S69: PLANNING ` | AA69: DESIGNS • Protective and mitigating measures due to the risk of increased resistance in extreme temperatures causing decrease of efficiency and performance of power lines • Protective measures responding to possible ground shrink-ages causing damages to underground utilities ` | AI69: COMMUNITY DEVELOPMENT PLANS • Provide access to online platform to access climate risk data • For emergency cases, foresee resilient communication tool that helps coordinate essential communication during disaster risk, in case of ITC system disruption `
B70: =RVAT_Output!$AV371 -> Potable water | R70: =IF(OR(R71=$R$36,R74=$R$36,R82=$R$36),$R$36,$R$35) -> Not High | S70: .
C71: =RVAT_Output!AW371 -> Access | F71: =RVAT_Output!AZ371 -> Low | L71: =RVAT_Output!BF371 -> Low | R71: =IF(OR(R72=$R$36,R75=$R$36,R83=$R$36),$R$36,$R$35) -> Not High | S71: PLANNING • The Consultant shall demonstratedly address resiliency of the water supply system by making provisions for water supply / delivery; water quality; and water quality, based on a thorough existing conditions assessment as well as demand study. • The water supply planning shall be watershed based and use gravity flows • Siting of water pipes in flood plains must be avoided. • Siting of water access points in flood plains shall not be undertaken. Consider different needs depending on gender, age and abilities ` | AA71: DESIGNS • Design for a resilient water supply system by making provisions for water supply and delivery; water quality; and water quality, based on a thorough existing conditions assessment as well as demand study • Any design must respond to the water availability besides demand and make provisions accordingly. • Plan boreholes at minimum distance of 100 m from sources of pollution • The Consultant shall closely engage and confirm the designs with the local water boards and present agreement on the plan and water supply capacity requirements with conformed solutions. • Designs must consider the local water pressures. • Foresee sufficient number of water extraction points for maximum extraction for every identified water source to not exceed natural recharge • Foresee provisions to ensure availability of sufficient quantities of water in dry seasons and during interrupted water supply by installing sufficient water storage and ensure timely filling in conjunction with the water authorities ` | AI71: COMMUNITY DEVELOPMENT PLANS • There shall be use of solar powered pumps for extraction of borehole water • The location of water access points, despite respecting environmental conditions and restrictions to the siting of water access points, must also provenly be gender sensitive and responsive. • Foresee promotion of rainwater harvesting through awareness campaigns and facilitation of access to finance for rainwater storage and private households • Foresee accompanying programs that facilitate micro finance for access to water tanks that will contribute to securing access to water during dry periods Consider different needs depending on gender, age and abilities `
C72: =RVAT_Output!AW372 -> Scarcities | F72: =RVAT_Output!AZ372 -> Low | L72: =RVAT_Output!BF372 -> Low | R72: =IF(OR(R73=$R$36,R76=$R$36,R84=$R$36),$R$36,$R$35) -> Not High | S72: PLANNING • determine enough water extraction points for maximum extraction for every identified water source to not exceed natural recharge ` | AA72: DESIGNS • The Consultant shall take into account integration with water demand for the case where sewerage systems are proposed as part of the design and confirm with the responsible authority equally. ` | AI72: COMMUNITY DEVELOPMENT PLANS • The optimum size of water tanks for households to install to cover large portions of dry periods shall be calculated (which should be communicated through awareness programs, and access facilitated though micro finance programs) `
C73: =RVAT_Output!AW373 -> Quality | F73: =RVAT_Output!AZ373 -> Low | L73: =RVAT_Output!BF373 -> Low | R73: =IF(OR(R74=$R$36,R77=$R$36,R85=$R$36),$R$36,$R$35) -> Not High | S73: PLANNING • Land uses and facilities that may pollute ground water must be adequately distant • Locate potentially polluting land uses in adequate distance from fresh water bodies and water extraction points, considering main wind directions • Protect fresh water bodies and water extraction points from potential sources of effluent discharges associated storm and wind surges • Protect ground water extraction points from pollution • Address the cause of pollution as a priority intervention Take measures to prevent sedimentation • Create vegetative barriers to prevent debris from flushing onto water bodies • Verify types of agricultural uses and practices in relation to potential sources of pollution, and address water pollution ` | AA73: DESIGNS ` | AI73: COMMUNITY DEVELOPMENT PLANS • Foresee measures to prevent pollution of fresh water bodies and water extraction points from debris / floatsome and effluent discharge associated with storm and wind surges • Prevent water pollution from debris / floatsome and effluent discharge `
B74: =RVAT_Output!$AV375 -> EBS | R74: =IF(OR(R75=$R$36,R78=$R$36,R86=$R$36),$R$36,$R$35) -> Not High | S74: .
C75: =RVAT_Output!AW375 -> Soil | F75: =RVAT_Output!AZ375 -> Low | L75: =RVAT_Output!BF375 -> Low | R75: =IF(OR(R76=$R$36,R79=$R$36,R87=$R$36),$R$36,$R$35) -> Not High | S75: PLANNING • Do not allow settlement expansion in steep terrain with clayey and sandy soils avoid major infrastructure construction and road network increase on clayey soils and hilly terrain ` | AA75: DESIGNS • Foresee natural erosion control measures ` | AI75: COMMUNITY DEVELOPMENT PLANS • Create awareness about importance of avoiding grey water release into environment as part of flood prevention and importance of maintaining infiltration capacity • Create awareness of risks associated with different types of soils • Foresee soil improvement and restoration programs especially in areas prone to drought and food insecurity `
C76: =RVAT_Output!AW376 -> LC & P | F76: =RVAT_Output!AZ376 -> Low | L76: =RVAT_Output!BF376 -> Low | R76: =IF(OR(R77=$R$36,R80=$R$36,R88=$R$36),$R$36,$R$35) -> Not High | S76: PLANNING • Require adequate percentage and distribution of vegetative ground cover and closed canopy to mitigate extreme heat; • Road upgrading must be planned in a way to minimize/ avoid cutting down of trees in the road corridor • There shall be nature-based solutions with respect to natural ecosystems, storm water flow path and ground water and soil conditions. ` | AA76: DESIGNS • Adopt natura based design solutions, such as bioswales, ponds ` | AI76: COMMUNITY DEVELOPMENT PLANS • Loss of vegetation cover is actively minimized/ prevented • Protect forests and woodlands • Increase tree cover • Promote upkeep of grazing areas • Reinstate vegetative cover • Rebuild mangrove forests in coastal areas `
C77: =RVAT_Output!AW377 -> NV | F77: =RVAT_Output!AZ377 -> Low | L77: =RVAT_Output!BF377 -> Low | R77: =IF(OR(R78=$R$36,R81=$R$36,R89=$R$36),$R$36,$R$35) -> Not High | S77: PLANNING • Ensure protection of forested areas as part of the planning process • Foresee reinstatement and enhancement of vegetative cover • Ensure protection of forested areas as part of the planning process, by means of land use planning, and supported by regulatory measures and physical means (green fences, barriers, etc…) ` | AA77: DESIGNS • Adopt natura based design solutions ` | AI77: COMMUNITY DEVELOPMENT PLANS • In coastal locations, consider including a mangrove nursery project where feasible (which could contribute to LED) • In areas prone to extreme temperature and drought, foresee tree planting of indigenous species • Actively prevent deforestation `
C78: =RVAT_Output!AW378 -> Wetland | F78: =RVAT_Output!AZ378 -> Low | L78: =RVAT_Output!BF378 -> Low | R78: =IF(OR(R79=$R$36,R82=$R$36,R90=$R$36),$R$36,$R$35) -> Not High | S78: PLANNING • Integrate natural wetlands in land use planning and ensure their safeguarding • Protect and reinstate if applicable any wetland areas and foresee enforcement measures to maintain their natural functionality ` | AA78: DESIGNS • Surface areas that wash into storm drains clean must be free from animal dung, toxic chemicals, fertilizers and motor oil • Use only native plant species when foreseeing plants in and near wetlands • Foresee slope stabilizing measures with native wetland vegetation ` | AI78: COMMUNITY DEVELOPMENT PLANS • Protect functionality of wetlands • Promote functionality of mangrove ecosystems • Undertake awareness, information and enforcement options of environmental regulations to sensitize, audit and make accountable large-scale industries on illegal pollution and discharges • Include wetland maintenance and regular solid waste removal as part of SWM plans • Foresee sediment removal from wetlands (infrequent) `
C79: =RVAT_Output!AW379 -> Biodiversity | F79: =RVAT_Output!AZ379 -> Low | L79: =RVAT_Output!BF379 -> Low | R79: =IF(OR(R80=$R$36,R83=$R$36,R91=$R$36),$R$36,$R$35) -> Not High | S79: PLANNING • Ensure respect to areas for undisturbed habitat/nisting/and migrational routes for conservation purposes and to mitigate human wildlife conflict • Support connectivity of natural unbuilt areas ` | AA79: DESIGNS ` | AI79: COMMUNITY DEVELOPMENT PLANS `
C80: =RVAT_Output!AW380 -> NWB | F80: =RVAT_Output!AZ380 -> Low | L80: =RVAT_Output!BF380 -> Low | R80: =IF(OR(R81=$R$36,R84=$R$36,R92=$R$36),$R$36,$R$35) -> Not High | S80: PLANNING • Support denitrification of rivers by consideration at the planning and design stages • Ensure respect to the river bed and flood plain of any nearby water bodies; ensure protection of ground water ad springs from pollution through adequate siting and distancing of land uses and facilities that may adversely impact water quality • Ensure respect to the river bed and flood plain of any nearby water bodies; ensure protection of ground water ad springs from pollution through adequate siting and distancing of land uses and facilities that may adversely impact water quality • Stream modification, such as realignment or relocation must not be permitted. Where such modifications have taken place in the past, natural conditions shall be reinstated as far as feasible as part of the LPLUDP proposal. • Preserve critical ecosystems, include ecosystem reinstatement measures where applicable ` | AA80: DESIGNS • Integrate nature-based solutions as biofilters for denitrification of surface runoff, subsurface and ground water ` | AI80: COMMUNITY DEVELOPMENT PLANS • Foresee measures with the objective of improving water quality of rivers `
C81: =RVAT_Output!AW381 -> Sea | F81: =RVAT_Output!AZ381 -> Low | L81: =RVAT_Output!BF381 -> Low | R81: =IF(OR(R82=$R$36,R85=$R$36,R93=$R$36),$R$36,$R$35) -> Not High | S81: PLANNING • Ensure respect to sea and tidal movements and undertake land use siting accordingly • Avoid inappropriate development in vulnerable coastal areas ` | AA81: DESIGNS ` | AI81: COMMUNITY DEVELOPMENT PLANS • Undertake awareness programs on respecting the seashore, and preventing pollution `
C82: =RVAT_Output!AW382 -> EF | F82: =RVAT_Output!AZ382 -> Low | L82: =RVAT_Output!BF382 -> Low | R82: =IF(OR(R83=$R$36,R86=$R$36,R94=$R$36),$R$36,$R$35) -> Not High | S82: PLANNING • Protect and reinstate if applicable any wetland areas and foresee enforcement measures to maintain their natural functionality • Preserve critical ecosystems, include ecosystem reinstatement measures where applicable • Restore / protect riparian zones from inadequate land use ` | AA82: DESIGNS • Respect storm water flow paths, flood plains and natural ecosystems when designing infrastructure ` | AI82: COMMUNITY DEVELOPMENT PLANS • Foresee measures with the objective of improving water quality of rivers, where applicable (awareness and information) • Foresee investment in ecosystem restoration • Consider soil restoration projects where applicable and feasible • Facilitate finance programs for upgrading of industrial technologies to mitigate pollution `
C83: =RVAT_Output!AW383 -> Land use | F83: =RVAT_Output!AZ383 -> Low | L83: =RVAT_Output!BF383 -> Low | R83: =IF(OR(R84=$R$36,R87=$R$36,R95=$R$36),$R$36,$R$35) -> Not High | S83: PLANNING • Require natural permeable areas in support of storm water infiltration and in response to storm water flow paths • Avoid inappropriate development in vulnerable coastal areas • ensure land use planning and enforcement that discourages settling on inadequate land / risky areas; avoid inappropriate development in areas at risk of flooding. Where the development is necessary, ensure its safety without increasing flood risk elsewhere; • minimize road network density • In line with the National policy (National CC Action Plan), it must be ensured that consideration of the following is evident in the elaboration of the LPLUDP’s: • Forest land must be protected / Degraded landscapes should be restored / Terrestrial and inland water conservation areas must be respected / Dispersal areas and migratory pathways must be respected / Water catchment areas must be conserved • As part of both vulnerability reduction and climate change mitigation efforts, the LPLUDP’s shall further integrate demonstrated consideration that, as applicable: functionality of wetlands actively is protected / Functionality of mangroves is actively promoted / Restoration of riparian zones is promoted / Deforestation is actively prevented / o Loss of vegetation cover is actively /minimized/ prevented / Tree cover is increased / o Upkeep of grazing areas is promoted. • ensure land use planning and enforcement that discourages settling on inadequate land / risky areas • Address the cause of pollution as a priority intervention ` | AA83: DESIGNS • Respect land use plans ` | AI83: COMMUNITY DEVELOPMENT PLANS • Undertake awareness and information about land use sensitivities, hazardous areas and location based hazard risks and zones which must not be settled on for public health and safety, and environmental reasons `
C84: =RVAT_Output!AW384 -> Topography | F84: =RVAT_Output!AZ384 -> Low | L84: =RVAT_Output!BF384 -> Low | R84: =IF(OR(R85=$R$36,R88=$R$36,R96=$R$36),$R$36,$R$35) -> Not High | S84: PLANNING • Combine vegetative soil stabilization measures with adaptive road network planning and storm water management planning; • minimize road network density; minimize road network on steep terrain • Major road network increase shall be avoided on clayey soils and steep slopes ` | AA84: DESIGNS • avoid road construction and embankments on steep slopes ` | AI84: COMMUNITY DEVELOPMENT PLANS • Undertake awareness and information campaigns to prevent construction on steep slopes • Undertake information campaigns on safe construction `
B85: =RVAT_Output!$AV386 -> Institutions | R85: =IF(OR(R86=$R$36,R89=$R$36,R97=$R$36),$R$36,$R$35) -> Not High | S85: .
C86: =RVAT_Output!AW386 -> EWS | F86: =RVAT_Output!AZ386 -> Low | L86: =RVAT_Output!BF386 -> Low | R86: =IF(OR(R87=$R$36,R90=$R$36,R98=$R$36),$R$36,$R$35) -> Not High | S86: PLANNING • Ensure registration of all households ` | AA86: DESIGNS ` | AI86: COMMUNITY DEVELOPMENT PLANS • Institutionalise an early warning system • Establish a method of availing climate data (rainfall precipitation, desertification) to transmit timely warnings to the community • The Consultant should elaborate an Evacuation Plan for the community including Standard Operational Procedures (SOPs). • An Evacuation Plan must include: o Evacuation routes / o Identified mapped critical assets /o Measures proposed to safeguard the critical assets (and to plan for their implementation)/o Identified evacuation shelter /o Actors with assigned responsibilities. `
C87: =RVAT_Output!AW387 -> A & I | F87: =RVAT_Output!AZ387 -> Low | L87: =RVAT_Output!BF387 -> Low | R87: =IF(OR(R88=$R$36,R91=$R$36,R99=$R$36),$R$36,$R$35) -> Not High | S87: PLANNING • Before stat of planning, explain KISIP process chart on implementation processes, focal points and contacts, roles and responsibilities in the processes, details of the plan and design elaboration processes, opportunities for the communities to voice their concerns and needs, expectations from SEC ` | AA87: DESIGNS • Create awareness about importance of infrastructure maintenance to sustain its functionality ` | AI87: COMMUNITY DEVELOPMENT PLANS • The plan shall establish how awareness and knowledge of the warning system and of SOPs will be created among all community members • Train SEC's as ToT, and plan for awareness and information campaigns for communities on • understanding about the effects of climate change and severe weather events on the community in general • understanding of the identified location-based risks relevant to the settlement where the SEC is established, along with the aspects that amplify the risks and vulnerabilities • linkage between the residents’ vulnerabilities and effects on critical assets and facilities, and behavioural aspects such as waste dumping and building within stormwater pathways • awareness about unhabitable zones and ecosystems that must not be disturbed, the reasons for this, and ways of sensitizing residents and assisting them as part of KISIP program interventions • intense training about the implementation of DRM plans/ evacuation plans once available, for SEC to become ToT • opportunities of GHG reductions in the private domestic and business realm, and programs supporting access to finance once available as part of CDP’s Consider different needs and way of accessing information depending on gender, age and abilities `
C88: =RVAT_Output!AW388 -> EC | F88: =RVAT_Output!AZ388 -> Low | L88: =RVAT_Output!BF388 -> Low | R88: =IF(OR(R89=$R$36,R92=$R$36,R100=$R$36),$R$36,$R$35) -> Not High | S88: PLANNING • County to support us of tool A and B ` | AA88: DESIGNS • County to support use of Tool C • County to collect information of maintenance requirements for the planned infrastructure interventions, and cost projections of the maintenance costs and type of requirements ` | AI88: COMMUNITY DEVELOPMENT PLANS • Plan awareness and information programs on: • KISIP processes, Effects of climate change and severe weather events on the community, identified location-based risks relevant to the settlement, unhabitable zones and ecosystems that must not be disturbed, access to early warning information and functioning of the system, DRM Plans and evacuation plans, access to climate related information, opportunities of GHG reductions, Knowledge on crop diversification, risk of overfishing, causes of pollution, causes of health risks and vulnerabilities • Provide opportunity to follow up on maintenance budget in the County budget • Create PPP in SWM `
C89: =RVAT_Output!AW389 -> R/RP | F89: =RVAT_Output!AZ389 -> Low | L89: =RVAT_Output!BF389 -> Low | R89: =IF(OR(R90=$R$36,R93=$R$36,R101=$R$36),$R$36,$R$35) -> Not High | S89: PLANNING ` | AA89: DESIGNS ` | AI89: COMMUNITY DEVELOPMENT PLANS • The locations of all critical infrastructure (especially health facilities, schools, evacuation centres, water and sanitation, settlement access roads, water treatment facilities, etc must be clearly identified. `
C90: =RVAT_Output!AW390 -> HFO | F90: =RVAT_Output!AZ390 -> Low | L90: =RVAT_Output!BF390 -> Low | R90: =IF(OR(R91=$R$36,R94=$R$36,R102=$R$36),$R$36,$R$35) -> Not High | S90: PLANNING • Protect health facilities from hazards by placing in safe locations ` | AA90: DESIGNS • foresee protective measures for health facilities that ensure their resiliency (adequate drainage, infiltration) ` | AI90: COMMUNITY DEVELOPMENT PLANS • foresee protective measures that ensure access to water and electricity, budget for and equip with generators and water tanks, etc `
C91: =RVAT_Output!AW391 -> DP | F91: =RVAT_Output!AZ391 -> Low | L91: =RVAT_Output!BF391 -> Low | R91: =IF(OR(R92=$R$36,R95=$R$36,R103=$R$36),$R$36,$R$35) -> Not High | S91: ` | AA91: DESIGNS • Plan for measures (e.g. levees and dykes) that protect the critical infrastructures from identified flash flood flow paths and hydrological conditions during flood and intense precipitation • Plan for measures to safeguard groundwater, landfill sites and sewage treatment sites to control pollution • Plan for measures to safeguard pit latrines and septic tanks from overflow and spilling of faeces into the environment (environmental and public health subject) ` | AI91: COMMUNITY DEVELOPMENT PLANS • Identify safe evacuation routes that are not at risk of flooding, and include in the Evacuation Plan • Raise awareness and inform all community members about the locations for evacuation shelter and evacuation routes • Determine evacuation facilities in safe locations and include in the Evacuation Plan; For settlements at risk of flood or flash flood hazard and intense precipitation, the location must be elevated, with access to water and sanitation, well ventilated/ For settlements at risk of drought and extreme temperature, there must be access to water and sanitation at the location, the facility shall be well ventilated, and have reflective roofing • Plan for the prepositioning of tents and camp management in situ • In addition, for settlements at risk of drought, plan for tents and camp management in migration destinations • Develop a mechanism that will be used to provide prepositioned emergency medicine/first aid kits/ dignity kits • For settlements at risk of flood or flash flood hazard and intense precipitation, predisposition cholera medication • For settlements at risk of drought and extreme temperature, predisposition dehydration and malnutrition treatment. • Pre-identify persons trained in first aid/ensure training of SEC and community members • Develop a mechanism that will be used to provide information for access to health care in cases of disaster and prepare such information • Develop a mechanism that will make accessible psycho-social support in cases of disaster • Pre-identify and create awareness of safe spaces for women and children • Develop a mechanism that will install hospital referral system for cases of disaster • Predetermine a mechanism and predisposition the equipment for rescue from flood waters • Help ensuring enrolment in national health insurance fund (NHIF) Consider different responses depending on gender, age and abilities (refer to Table C-2) `
C92: =RVAT_Output!AW392 -> DR | F92: =RVAT_Output!AZ392 -> Low | L92: =RVAT_Output!BF392 -> Low | R92: =IF(OR(R93=$R$36,R96=$R$36,R104=$R$36),$R$36,$R$35) -> Not High | S92: PLANNING ` | AA92: DESIGNS ` | AI92: COMMUNITY DEVELOPMENT PLANS • Foresee mechanism that immediately reinstates accessibility of relevant critical facilities during extreme weather events; • Foresee emergency responses, e.g. emergency care for patients in potentially affected hospitals • Foresee mechanism to immediately control effects of severe weather events and disaster onto water and the environment (such as effluent of hazardous substances) • Budget for provision of evacuation shelter, health services, food, education, maintained livelihood, access to finance in case of disaster • Foresee training of community members in disaster response and first aid Consider different needs depending on gender, age and abilities (refer to Table C-2) `
C93: =RVAT_Output!AW393 -> PFR | F93: =RVAT_Output!AZ393 -> Low | L93: =RVAT_Output!BF393 -> Low | R93: =IF(OR(R94=$R$36,R97=$R$36,R105=$R$36),$R$36,$R$35) -> Not High | S93: PLANNING • Identify options for access to adaptation funding for necessitated relocations from high risk areas and for reinstalment assistance Consider different needs depending on gender, age and abilities ` | AA93: DESIGNS • Foresee adequate areas formally available to practice subsistence agriculture and keep livestock • Plan for land uses and accompanying programs that support diversification of livelihoods • Plan construction of abattoirs • Mitigate land use conversion of fertile soils, and assign appropriate sites for settlement growth ` | AI93: COMMUNITY DEVELOPMENT PLANS • Develop a mechanism to ensure quick repair of access roads to markets and commercial areas • Foresee disaster recovery funding as part of County budget • Identify external sources and funding opportunities for disaster and climate adaptation funding • Advocate for making disaster risk insurances for households and SME’s accessible and affordable under loss and damage budgets Consider different needs depending on gender, age and abilities `
C94: =RVAT_Output!AW394 -> PFM | F94: =RVAT_Output!AZ394 -> Low | L94: =RVAT_Output!BF394 -> Low | R94: =IF(OR(R95=$R$36,R98=$R$36,R106=$R$36),$R$36,$R$35) -> Not High | S94: PLANNING • County to consider budget for ecosystem restoration ` | AA94: DESIGNS • County to collect information of maintenance requirements for the planned infrastructure interventions, and cost projections of the maintenance costs and type of requirements ` | AI94: COMMUNITY DEVELOPMENT PLANS • Establish PPPs in maintenance and solid waste management • Consider cross-subsidization of waste removal fees for vulnerable households • Consider increase of maintenance costs for roads in areas facing extreme heat and drought, and in areas frequently facing flooding, if not adopting resilient designs • Plan for regular inspection of critical infrastructures facing extreme weather conditions to maintain their safety • Undertake awareness and information campaign on not littering, not to dispose waste in uncontrolled manner `
K106: High | L106: Med
C186: Risk 1
C187: =RVAT_Output!B280 -> Livelihoods | E187: =RVAT_Output!D280 -> Health & Safety | I187: =RVAT_Output!H280 -> Assets and Utilities | O187: =RVAT_Output!N280 -> Potable water | V187: =RVAT_Output!U280 -> EBS | Z187: =RVAT_Output!Y280 -> Institutions
C189: =RVAT_Output!B282 -> Low | E189: =RVAT_Output!D282 -> Low | I189: =RVAT_Output!H282 -> Low | O189: =RVAT_Output!N282 -> Low | V189: =RVAT_Output!U282 -> Low | Z189: =RVAT_Output!Y282 -> Low
C191: Risk 2
C192: =RVAT_Output!B285 -> Livelihoods | D192: =RVAT_Output!C285 -> Food Security | E192: =RVAT_Output!D285 -> Grazing/Farm Land | G192: =RVAT_Output!F285 -> Crops | I192: =RVAT_Output!H285 -> Livestock | L192: =RVAT_Output!K285 -> Fishstock | O192: =RVAT_Output!N285 -> Local commerce | S192: =RVAT_Output!R285 -> Gender | V192: =RVAT_Output!U285 -> Conviviality | Y192: =RVAT_Output!X285 -> Education | Z192: =RVAT_Output!Y285 -> WFI/WFDU | AA192: =RVAT_Output!Z285 -> ATF/I | AB192: =RVAT_Output!AA285 -> Disaster Events
C193: =RVAT_Output!B286 -> Health & Safety | D193: =RVAT_Output!C286 -> Borne Diseases | E193: =RVAT_Output!D286 -> SLUP&C | H193: =RVAT_Output!G286 -> SWM | M193: =RVAT_Output!L286 -> LWM | S193: =RVAT_Output!R286 -> ATHS | Z193: =RVAT_Output!Y286 -> ATHE
C194: =RVAT_Output!B287 -> Assets and Utilities | D194: =RVAT_Output!C287 -> Housing | E194: =RVAT_Output!D287 -> Public facilities | G194: =RVAT_Output!F287 -> SWD | I194: =RVAT_Output!H287 -> Sanitary facilities | L194: =RVAT_Output!K287 -> Sewer lines | O194: =RVAT_Output!N287 -> Power lines/supply | S194: =RVAT_Output!R287 -> Energy for HH use | V194: =RVAT_Output!U287 -> Water pipes | Y194: =RVAT_Output!X287 -> PWT | Z194: =RVAT_Output!Y287 -> Water Storage | AA194: =RVAT_Output!Z287 -> R & T | AB194: =RVAT_Output!AA287 -> Communication | AH194: `
C195: =RVAT_Output!B288 -> Potable water | D195: =RVAT_Output!C288 -> Access | K195: =RVAT_Output!J288 -> Scarcities | Y195: =RVAT_Output!X288 -> Quality
C196: =RVAT_Output!B289 -> EBS | D196: =RVAT_Output!C289 -> Soil | E196: =RVAT_Output!D289 -> LC & P | H196: =RVAT_Output!G289 -> NV | K196: =RVAT_Output!J289 -> Wetland | N196: =RVAT_Output!M289 -> Biodiversity | S196: =RVAT_Output!R289 -> NWB | Y196: =RVAT_Output!X289 -> Sea | Z196: =RVAT_Output!Y289 -> EF | AA196: =RVAT_Output!Z289 -> Land use | AB196: =RVAT_Output!AA289 -> Topography
C197: =RVAT_Output!B290 -> Institutions | D197: =RVAT_Output!C290 -> EWS | E197: =RVAT_Output!D290 -> A & I | H197: =RVAT_Output!G290 -> EC | L197: =RVAT_Output!K290 -> R/RP | P197: =RVAT_Output!O290 -> HFO | W197: =RVAT_Output!V290 -> DP | Z197: =RVAT_Output!Y290 -> DR | AA197: =RVAT_Output!Z290 -> PFR | AB197: =RVAT_Output!AA290 -> PFM
C199: =C192 -> Livelihoods | D199: =RVAT_Output!C292 -> Low | E199: =RVAT_Output!D292 -> Low | G199: =RVAT_Output!F292 -> Low | I199: =RVAT_Output!H292 -> Low | L199: =RVAT_Output!K292 -> Low | O199: =RVAT_Output!N292 -> Low | S199: =RVAT_Output!R292 -> Low | V199: =RVAT_Output!U292 -> Low | Y199: =RVAT_Output!X292 -> Low | Z199: =RVAT_Output!Y292 -> Low | AA199: =RVAT_Output!Z292 -> Low | AB199: =RVAT_Output!AA292 -> Low
C200: =C193 -> Health & Safety | D200: =RVAT_Output!C293 -> Low | E200: =RVAT_Output!D293 -> Low | H200: =RVAT_Output!G293 -> Low | M200: =RVAT_Output!L293 -> Low | S200: =RVAT_Output!R293 -> Low | Z200: =RVAT_Output!Y293 -> Low
C201: =C194 -> Assets and Utilities | D201: =RVAT_Output!C294 -> Low | E201: =RVAT_Output!D294 -> Low | G201: =RVAT_Output!F294 -> Low | I201: =RVAT_Output!H294 -> Low | L201: =RVAT_Output!K294 -> Low | O201: =RVAT_Output!N294 -> Low | S201: =RVAT_Output!R294 -> Low | V201: =RVAT_Output!U294 -> Low | Y201: =RVAT_Output!X294 -> Low | Z201: =RVAT_Output!Y294 -> Low | AA201: =RVAT_Output!Z294 -> Low | AB201: =RVAT_Output!AA294 -> Low
C202: =C195 -> Potable water | D202: =RVAT_Output!C295 -> Low | K202: =RVAT_Output!J295 -> Low | Y202: =RVAT_Output!X295 -> Low
C203: =C196 -> EBS | D203: =RVAT_Output!C296 -> Low | E203: =RVAT_Output!D296 -> Low | H203: =RVAT_Output!G296 -> Low | K203: =RVAT_Output!J296 -> Low | N203: =RVAT_Output!M296 -> Low | S203: =RVAT_Output!R296 -> Low | Y203: =RVAT_Output!X296 -> Low | Z203: =RVAT_Output!Y296 -> Low | AA203: =RVAT_Output!Z296 -> Low | AB203: =RVAT_Output!AA296 -> Low
C204: =C197 -> Institutions | D204: =RVAT_Output!C297 -> Low | E204: =RVAT_Output!D297 -> Low | H204: =RVAT_Output!G297 -> Low | L204: =RVAT_Output!K297 -> Low | P204: =RVAT_Output!O297 -> Low | W204: =RVAT_Output!V297 -> Low | Z204: =RVAT_Output!Y297 -> Low | AA204: =RVAT_Output!Z297 -> Low | AB204: =RVAT_Output!AA297 -> Low
C206: Vulnurability 2
C207: =RVAT_Output!B260 -> Livelihoods | E207: =RVAT_Output!D260 -> Health & Safety | I207: =RVAT_Output!H260 -> Assets and Utilities | O207: =RVAT_Output!N260 -> Potable water | V207: =RVAT_Output!U260 -> EBS | Z207: =RVAT_Output!Y260 -> Institutions
C209: =RVAT_Output!B262 -> Low | E209: =RVAT_Output!D262 -> Low | I209: =RVAT_Output!H262 -> Low | O209: =RVAT_Output!N262 -> Low | V209: =RVAT_Output!U262 -> Low | Z209: =RVAT_Output!Y262 -> Low
...
